{
    "_shards": {
        "failed": 0,
        "successful": 5,
        "total": 5
    },
    "hits": {
        "hits": [
            {
                "_id": "336221928403173676",
                "_index": "pinterest",
                "_score": 1.0078546,
                "_source": {
                    "board": "336221997119939962",
                    "comment_count": "0",
                    "created": "Sat, 01 Mar 2014 20:36:15 +0000",
                    "description": "Hey, ho trovato questa fantastica inserzione di Etsy su https://www.etsy.com/it/listing/98882742/fuoco-feather-accessori-per-capelli",
                    "domain": "etsy.com",
                    "id": "336221928403173676",
                    "image": "https://s-media-cache-ak0.pinimg.com/736x/73/a4/fe/73a4feee989bf554e9b863b04fc7b970.jpg",
                    "image236": "https://s-media-cache-ak0.pinimg.com/236x/73/a4/fe/73a4feee989bf554e9b863b04fc7b970.jpg",
                    "image60": "https://s-media-cache-ak0.pinimg.com/60x60/73/a4/fe/73a4feee989bf554e9b863b04fc7b970.jpg",
                    "is_banned": "",
                    "is_repin": "",
                    "likes": "1",
                    "pin_join": "73a4feee989bf554e9b863b04fc7b970",
                    "pinner": "336222065839330353",
                    "place": "",
                    "price": "0",
                    "price_currency": "USD",
                    "repins": "1",
                    "source": "https://www.etsy.com/it/listing/98882742/fuoco-feather-accessori-per-capelli",
                    "title": "Fire Orange Hair Feathers Wholesale Feather Extensions Bulk Feather Hair Accessories - Salon Extension Feathers, 30 Pieces",
                    "type": "pin",
                    "url": "https://www.pinterest.com/pin/336221928403173676/",
                    "via_pinner": ""
                },
                "_type": "pin"
            },
            {
                "_id": "292030357057520077",
                "_index": "pinterest",
                "_score": 0.9826326,
                "_source": {
                    "board": "292030425776293443",
                    "comment_count": "0",
                    "created": "Tue, 26 Mar 2013 08:36:11 +0000",
                    "description": "Set of Featherstole & Feather Collar and Feather Cuffs ivory cream champaign Wrap bridal Shrug Bolero Burlesque Gogo Pole Samba Carneval. \u20ac69.50, via Etsy.",
                    "domain": "etsy.com",
                    "id": "292030357057520077",
                    "image": "https://s-media-cache-ak0.pinimg.com/736x/68/d2/00/68d200c5ab6a6bd1f73645200aaa3280.jpg",
                    "image236": "https://s-media-cache-ak0.pinimg.com/236x/68/d2/00/68d200c5ab6a6bd1f73645200aaa3280.jpg",
                    "image60": "https://s-media-cache-ak0.pinimg.com/60x60/68/d2/00/68d200c5ab6a6bd1f73645200aaa3280.jpg",
                    "is_banned": "",
                    "is_repin": "",
                    "likes": "0",
                    "pin_join": "68d200c5ab6a6bd1f73645200aaa3280",
                    "pinner": "292030494495744589",
                    "place": "",
                    "price": "0",
                    "price_currency": "USD",
                    "repins": "0",
                    "source": "http://www.etsy.com/listing/119375122/set-of-featherstole-feather-collar-and?ref=sr_gallery_43&ga_search_query=feather+bolero&ga_view_type=gallery&ga_ship_to=NZ&ga_ref=auto1&ga_search_type=all&ga_facet=feather+bolero",
                    "title": "Cool portraits",
                    "type": "pin",
                    "url": "https://www.pinterest.com/pin/292030357057520077/",
                    "via_pinner": ""
                },
                "_type": "pin"
            },
            {
                "_id": "389772542719864527",
                "_index": "pinterest",
                "_score": 0.81285954,
                "_source": {
                    "board": "389772611439068945",
                    "comment_count": "0",
                    "created": "Sat, 05 Jan 2013 02:41:03 +0000",
                    "description": "Blush Feather Dress 5105 BL-5105sp  www.dresseswd.com  Style: BL-5105sp  Name: Blush Feather Dress 5105  Details: Ruffled Bodice, Ruched Waist  Length: Long  Neckline: Strapless  Waistline: Empire",
                    "domain": "dresseswd.com",
                    "id": "389772542719864527",
                    "image": "https://s-media-cache-ak0.pinimg.com/736x/22/2a/ff/222affeccc204dcae89fd1b730c855f4.jpg",
                    "image236": "https://s-media-cache-ak0.pinimg.com/236x/22/2a/ff/222affeccc204dcae89fd1b730c855f4.jpg",
                    "image60": "https://s-media-cache-ak0.pinimg.com/60x60/22/2a/ff/222affeccc204dcae89fd1b730c855f4.jpg",
                    "is_banned": "",
                    "is_repin": "",
                    "likes": "0",
                    "pin_join": "222affeccc204dcae89fd1b730c855f4",
                    "pinner": "389772680158527804",
                    "place": "",
                    "price": "0",
                    "price_currency": "USD",
                    "repins": "0",
                    "source": "http://www.dresseswd.com/shop-by-brand/blush/blush-feather-dress-5105-strapless-bl-5105sp.html",
                    "title": "Blush Prom Dresses",
                    "type": "pin",
                    "url": "https://www.pinterest.com/pin/389772542719864527/",
                    "via_pinner": ""
                },
                "_type": "pin"
            },
            {
                "_id": "438326976203868706",
                "_index": "pinterest",
                "_score": 0.7955643,
                "_source": {
                    "board": "438327044921680684",
                    "comment_count": "0",
                    "created": "Sat, 21 Sep 2013 13:39:37 +0000",
                    "description": "SS: Ostrich Feather Tick. Asst. (6/DP) by Sportsheets International, Inc.. $53.51. Ostrich Feather Ticklers Display (Assorted)Luxurious, genuine ostrich feather will keep the most shy partner from burying their head in the sand.Includes 6.",
                    "domain": "tepclock.com",
                    "id": "438326976203868706",
                    "image": "https://s-media-cache-ak0.pinimg.com/736x/d8/4d/d6/d84dd65e2ea24ba9773638ab97192384.jpg",
                    "image236": "https://s-media-cache-ak0.pinimg.com/236x/d8/4d/d6/d84dd65e2ea24ba9773638ab97192384.jpg",
                    "image60": "https://s-media-cache-ak0.pinimg.com/60x60/d8/4d/d6/d84dd65e2ea24ba9773638ab97192384.jpg",
                    "is_banned": "",
                    "is_repin": "",
                    "likes": "0",
                    "pin_join": "d84dd65e2ea24ba9773638ab97192384",
                    "pinner": "438327113641112489",
                    "place": "",
                    "price": "53.51",
                    "price_currency": "USD",
                    "repins": "0",
                    "source": "http://tepclock.com/camba/dptyn/Bt0y0n2iIeYvGeBcQeSz.html",
                    "title": "Home & Kitchen",
                    "type": "pin",
                    "url": "https://www.pinterest.com/pin/438326976203868706/",
                    "via_pinner": ""
                },
                "_type": "pin"
            },
            {
                "_id": "485192559827589356",
                "_index": "pinterest",
                "_score": 0.7845586,
                "_source": {
                    "board": "485192628543951528",
                    "comment_count": "0",
                    "created": "Mon, 07 Apr 2014 06:23:43 +0000",
                    "description": "Hey, I found this really awesome Etsy listing at https://www.etsy.com/listing/183881578/gold-feather-captive-bead-hoop-cartilage",
                    "domain": "etsy.com",
                    "id": "485192559827589356",
                    "image": "https://s-media-cache-ak0.pinimg.com/736x/43/40/a4/4340a4f71d47e279d08577aa56db6370.jpg",
                    "image236": "https://s-media-cache-ak0.pinimg.com/236x/43/40/a4/4340a4f71d47e279d08577aa56db6370.jpg",
                    "image60": "https://s-media-cache-ak0.pinimg.com/60x60/43/40/a4/4340a4f71d47e279d08577aa56db6370.jpg",
                    "is_banned": "",
                    "is_repin": "",
                    "likes": "7",
                    "pin_join": "4340a4f71d47e279d08577aa56db6370",
                    "pinner": "485192697263423650",
                    "place": "",
                    "price": "0",
                    "price_currency": "USD",
                    "repins": "22",
                    "source": "https://www.etsy.com/listing/183881578/gold-feather-captive-bead-hoop-cartilage",
                    "title": "Gold Feather Captive Bead Hoop; Cartilage Earring;Helix Earring",
                    "type": "pin",
                    "url": "https://www.pinterest.com/pin/485192559827589356/",
                    "via_pinner": ""
                },
                "_type": "pin"
            },
            {
                "_id": "312085449147897202",
                "_index": "pinterest",
                "_score": 0.767248,
                "_source": {
                    "board": "312085517866921121",
                    "comment_count": "0",
                    "created": "Sun, 27 Jan 2013 22:52:44 +0000",
                    "description": "pink square mid century feather bowl planter Shawnee Pottery USA. $21.00, via Etsy.",
                    "domain": "etsy.com",
                    "id": "312085449147897202",
                    "image": "https://s-media-cache-ak0.pinimg.com/736x/1a/eb/6c/1aeb6c4d0abe3bc3fb0b7df1eaf51264.jpg",
                    "image236": "https://s-media-cache-ak0.pinimg.com/236x/1a/eb/6c/1aeb6c4d0abe3bc3fb0b7df1eaf51264.jpg",
                    "image60": "https://s-media-cache-ak0.pinimg.com/60x60/1a/eb/6c/1aeb6c4d0abe3bc3fb0b7df1eaf51264.jpg",
                    "is_banned": "",
                    "is_repin": "",
                    "likes": "0",
                    "pin_join": "1aeb6c4d0abe3bc3fb0b7df1eaf51264",
                    "pinner": "312085586586375619",
                    "place": "",
                    "price": "21",
                    "price_currency": "USD",
                    "repins": "3",
                    "source": "http://www.etsy.com/listing/106492000/pink-square-mid-century-feather-bowl?ref=sr_gallery_23&ga_search_query=planter&ga_view_type=gallery&ga_ship_to=US&ga_page=237&ga_search_type=vintage",
                    "title": "pink square mid century feather bowl planter Shawnee Pottery USA",
                    "type": "pin",
                    "url": "https://www.pinterest.com/pin/312085449147897202/",
                    "via_pinner": ""
                },
                "_type": "pin"
            },
            {
                "_id": "9359111695678238",
                "_index": "pinterest",
                "_score": 0.75987756,
                "_source": {
                    "board": "9359180414615491",
                    "comment_count": "1",
                    "created": "Sat, 17 Mar 2012 19:19:32 +0000",
                    "description": "Silver plated Peacock Feather metal crochet Bracelet. I'm getting antsy for a wrist tattoo, so I need to quell my desire with some kick ass bracelets.",
                    "domain": "etsy.com",
                    "id": "9359111695678238",
                    "image": "https://s-media-cache-ak0.pinimg.com/736x/d1/7c/5f/d17c5fbf41092ed8dfa562ba4fabd2d0.jpg",
                    "image236": "https://s-media-cache-ak0.pinimg.com/236x/d1/7c/5f/d17c5fbf41092ed8dfa562ba4fabd2d0.jpg",
                    "image60": "https://s-media-cache-ak0.pinimg.com/60x60/d1/7c/5f/d17c5fbf41092ed8dfa562ba4fabd2d0.jpg",
                    "is_banned": "",
                    "is_repin": "",
                    "likes": "18",
                    "pin_join": "",
                    "pinner": "9359249134062038",
                    "place": "",
                    "price": "0",
                    "price_currency": "USD",
                    "repins": "73",
                    "source": "http://www.etsy.com/listing/89519202/silver-plated-peacock-feather-metal?ref=sr_gallery_34&sref=&ga_includes[0]=tags&ga_search_query=peacock+feather+bracelet&ga_ref=related&ga_page=1&ga_search_type=all&ga_facet=",
                    "title": "Silver plated Big Peacock Feather metal crochet Bracelet",
                    "type": "pin",
                    "url": "https://www.pinterest.com/pin/9359111695678238/",
                    "via_pinner": ""
                },
                "_type": "pin"
            },
            {
                "_id": "394416879838252564",
                "_index": "pinterest",
                "_score": 0.7137563,
                "_source": {
                    "board": "394416948554841370",
                    "comment_count": "0",
                    "created": "Mon, 27 Jan 2014 07:15:55 +0000",
                    "description": "Feather Necklace Antique Bronze Feather Owl Leaf by CottageJewelry",
                    "domain": "etsy.com",
                    "id": "394416879838252564",
                    "image": "https://s-media-cache-ak0.pinimg.com/736x/d2/ff/a6/d2ffa65244c8940ddb7797a3ff805114.jpg",
                    "image236": "https://s-media-cache-ak0.pinimg.com/236x/d2/ff/a6/d2ffa65244c8940ddb7797a3ff805114.jpg",
                    "image60": "https://s-media-cache-ak0.pinimg.com/60x60/d2/ff/a6/d2ffa65244c8940ddb7797a3ff805114.jpg",
                    "is_banned": "",
                    "is_repin": "",
                    "likes": "0",
                    "pin_join": "",
                    "pinner": "394417017274262646",
                    "place": "",
                    "price": "0",
                    "price_currency": "USD",
                    "repins": "1",
                    "source": "http://www.etsy.com/listing/177262119/feather-necklace-antique-bronze-feather?utm_source=Pinterest&utm_medium=PageTools&utm_campaign=Share",
                    "title": "Feather Necklace Antique Bronze Feather Owl Leaf Yellow Rose Necklace",
                    "type": "pin",
                    "url": "https://www.pinterest.com/pin/394416879838252564/",
                    "via_pinner": ""
                },
                "_type": "pin"
            },
            {
                "_id": "427067977134557121",
                "_index": "pinterest",
                "_score": 0.6888562,
                "_source": {
                    "board": "427068045853204423",
                    "comment_count": "0",
                    "created": "Mon, 22 Apr 2013 14:16:35 +0000",
                    "description": "Maxi dress low back Feather print coral mint Party by MuguetMilan",
                    "domain": "etsy.com",
                    "id": "427067977134557121",
                    "image": "https://s-media-cache-ak0.pinimg.com/736x/b1/5e/39/b15e39582e56b4177752b02f42d661e8.jpg",
                    "image236": "https://s-media-cache-ak0.pinimg.com/236x/b1/5e/39/b15e39582e56b4177752b02f42d661e8.jpg",
                    "image60": "https://s-media-cache-ak0.pinimg.com/60x60/b1/5e/39/b15e39582e56b4177752b02f42d661e8.jpg",
                    "is_banned": "",
                    "is_repin": "",
                    "likes": "0",
                    "pin_join": "",
                    "pinner": "427068114572675871",
                    "place": "",
                    "price": "0",
                    "price_currency": "USD",
                    "repins": "3",
                    "source": "http://www.etsy.com/listing/129555886/maxi-dress-low-back-feather-print-coral?share_id=20417131&hmac=4f644b0f9c33c7da7527246f199fce681846b8ca&utm_source=Pinterest&utm_medium=PageTools&utm_campaign=Share",
                    "title": "Maxi dress, low back. Feather print, coral, mint. Party, cocktail, prom. One size fits many. OOAK",
                    "type": "pin",
                    "url": "https://www.pinterest.com/pin/427067977134557121/",
                    "via_pinner": ""
                },
                "_type": "pin"
            },
            {
                "_id": "156570524520140383",
                "_index": "pinterest",
                "_score": 0.63662827,
                "_source": {
                    "board": "156570593234255897",
                    "comment_count": "0",
                    "created": "Tue, 04 Feb 2014 20:37:01 +0000",
                    "description": "Large FEATHER Hair Comb Verdigris Patina",
                    "domain": "etsy.com",
                    "id": "156570524520140383",
                    "image": "https://s-media-cache-ak0.pinimg.com/736x/ef/77/eb/ef77eb61a72847bb70ef62d5001ff2e0.jpg",
                    "image236": "https://s-media-cache-ak0.pinimg.com/236x/ef/77/eb/ef77eb61a72847bb70ef62d5001ff2e0.jpg",
                    "image60": "https://s-media-cache-ak0.pinimg.com/60x60/ef/77/eb/ef77eb61a72847bb70ef62d5001ff2e0.jpg",
                    "is_banned": "",
                    "is_repin": "",
                    "likes": "128",
                    "pin_join": "",
                    "pinner": "156570661953732609",
                    "place": "",
                    "price": "0",
                    "price_currency": "USD",
                    "repins": "522",
                    "source": "https://www.etsy.com/listing/162118815/large-feather-hair-comb-verdigris-patina?utm_source=Pinterest&utm_medium=PageTools&utm_campaign=Share",
                    "title": "Large FEATHER Hair Comb Verdigris Patina Autumn Woodland Whimsical Nature Bridal Green LEAF",
                    "type": "pin",
                    "url": "https://www.pinterest.com/pin/156570524520140383/",
                    "via_pinner": ""
                },
                "_type": "pin"
            },
            {
                "_id": "32721534765605006",
                "_index": "pinterest",
                "_score": 0.5733469,
                "_source": {
                    "board": "32721603481612799",
                    "comment_count": "0",
                    "created": "Mon, 10 Jun 2013 17:54:15 +0000",
                    "description": "Feather-Down Rectangular Pillow Inserts in Pillow Inserts | Crate and Barrel $8.00",
                    "domain": "crateandbarrel.com",
                    "id": "32721534765605006",
                    "image": "https://s-media-cache-ak0.pinimg.com/736x/5b/98/e0/5b98e08d9582243a888d7f037dd1f134.jpg",
                    "image236": "https://s-media-cache-ak0.pinimg.com/236x/5b/98/e0/5b98e08d9582243a888d7f037dd1f134.jpg",
                    "image60": "https://s-media-cache-ak0.pinimg.com/60x60/5b/98/e0/5b98e08d9582243a888d7f037dd1f134.jpg",
                    "is_banned": "",
                    "is_repin": "",
                    "likes": "0",
                    "pin_join": "5b98e08d9582243a888d7f037dd1f134",
                    "pinner": "32721672201048488",
                    "place": "",
                    "price": "8",
                    "price_currency": "USD",
                    "repins": "0",
                    "source": "http://www.crateandbarrel.com/feather-down-rectangular-pillow-inserts/f47229",
                    "title": "Feather-Down Rectangular Pillow Inserts",
                    "type": "pin",
                    "url": "https://www.pinterest.com/pin/32721534765605006/",
                    "via_pinner": ""
                },
                "_type": "pin"
            },
            {
                "_id": "484488872386374220",
                "_index": "pinterest",
                "_score": 0.5674018,
                "_source": {
                    "board": "484488941102284290",
                    "comment_count": "0",
                    "created": "Sat, 26 Apr 2014 22:17:05 +0000",
                    "description": "The #usedcar feather flag! A common flag used by #autodealerships everywhere. #featherflags #promotional",
                    "domain": "flickr.com",
                    "id": "484488872386374220",
                    "image": "https://s-media-cache-ak0.pinimg.com/736x/da/81/f6/da81f60c56395684b27ff4425b7ddca4.jpg",
                    "image236": "https://s-media-cache-ak0.pinimg.com/236x/da/81/f6/da81f60c56395684b27ff4425b7ddca4.jpg",
                    "image60": "https://s-media-cache-ak0.pinimg.com/60x60/da/81/f6/da81f60c56395684b27ff4425b7ddca4.jpg",
                    "is_banned": "",
                    "is_repin": "",
                    "likes": "0",
                    "pin_join": "",
                    "pinner": "484489009821665484",
                    "place": "",
                    "price": "0",
                    "price_currency": "USD",
                    "repins": "0",
                    "source": "https://www.flickr.com/photos/123915792@N04/14025276594/in/photostream/",
                    "title": "Feather Dancer Flags",
                    "type": "pin",
                    "url": "https://www.pinterest.com/pin/484488872386374220/",
                    "via_pinner": ""
                },
                "_type": "pin"
            },
            {
                "_id": "519321400751777935",
                "_index": "pinterest",
                "_score": 0.5612292,
                "_source": {
                    "board": "519321469470156161",
                    "comment_count": "0",
                    "created": "Wed, 12 Jun 2013 21:03:04 +0000",
                    "description": "Outstanding ANTIQUE1860S Civil War Era Princess Feather Quilt | eBay  Another favorite!",
                    "domain": "ebay.com",
                    "id": "519321400751777935",
                    "image": "https://s-media-cache-ak0.pinimg.com/736x/52/55/bc/5255bc4cc89cd2c03a4a95550f58f8ec.jpg",
                    "image236": "https://s-media-cache-ak0.pinimg.com/236x/52/55/bc/5255bc4cc89cd2c03a4a95550f58f8ec.jpg",
                    "image60": "https://s-media-cache-ak0.pinimg.com/60x60/52/55/bc/5255bc4cc89cd2c03a4a95550f58f8ec.jpg",
                    "is_banned": "",
                    "is_repin": "",
                    "likes": "0",
                    "pin_join": "",
                    "pinner": "519321538189599119",
                    "place": "",
                    "price": "0",
                    "price_currency": "USD",
                    "repins": "0",
                    "source": "http://www.ebay.com/itm/OUTSTANDING-ANTIQUE1860s-CIVIL-WAR-ERA-PRINCESS-FEATHER-QUILT-/370697387638?pt=Quilts&hash=item564f493e76",
                    "title": "OUTSTANDING ANTIQUE1860s CIVIL WAR ERA PRINCESS FEATHER QUILT",
                    "type": "pin",
                    "url": "https://www.pinterest.com/pin/519321400751777935/",
                    "via_pinner": ""
                },
                "_type": "pin"
            },
            {
                "_id": "514395588662459906",
                "_index": "pinterest",
                "_score": 0.55842566,
                "_source": {
                    "board": "514395657377867911",
                    "comment_count": "0",
                    "created": "Sat, 16 Aug 2014 02:45:22 +0000",
                    "description": "Morgan Fish 18x18-inch Feather Fill Throw Pillow",
                    "domain": "overstock.com",
                    "id": "514395588662459906",
                    "image": "https://s-media-cache-ak0.pinimg.com/736x/1a/93/cc/1a93ccc096813ab39b1434752ba2fb94.jpg",
                    "image236": "https://s-media-cache-ak0.pinimg.com/236x/1a/93/cc/1a93ccc096813ab39b1434752ba2fb94.jpg",
                    "image60": "https://s-media-cache-ak0.pinimg.com/60x60/1a/93/cc/1a93ccc096813ab39b1434752ba2fb94.jpg",
                    "is_banned": "",
                    "is_repin": "",
                    "likes": "0",
                    "pin_join": "1a93ccc096813ab39b1434752ba2fb94",
                    "pinner": "514395726097169620",
                    "place": "",
                    "price": "0",
                    "price_currency": "USD",
                    "repins": "0",
                    "source": "http://www.overstock.com/Home-Garden/Morgan-Fish-18x18-inch-Feather-Fill-Throw-Pillow/9036647/product.html?refccid=YLWJVHSXX7CIH7CL3VC7DAR3UE&searchidx=40",
                    "title": "Morgan Fish 18x18-inch Feather Fill Throw Pillow",
                    "type": "pin",
                    "url": "https://www.pinterest.com/pin/514395588662459906/",
                    "via_pinner": ""
                },
                "_type": "pin"
            },
            {
                "_id": "280419514268559589",
                "_index": "pinterest",
                "_score": 0.5561818,
                "_source": {
                    "board": "280419582986988826",
                    "comment_count": "0",
                    "created": "Tue, 05 Jun 2012 15:23:35 +0000",
                    "description": "Champagne Feather Flower Headpiece Set - Bridesmaid Feather Flower Fascinator. $64.95, via Etsy.",
                    "domain": "etsy.com",
                    "id": "280419514268559589",
                    "image": "https://s-media-cache-ak0.pinimg.com/736x/3d/35/89/3d35891f6a6cd5db5e8f7e99e8606bcc.jpg",
                    "image236": "https://s-media-cache-ak0.pinimg.com/236x/3d/35/89/3d35891f6a6cd5db5e8f7e99e8606bcc.jpg",
                    "image60": "https://s-media-cache-ak0.pinimg.com/60x60/3d/35/89/3d35891f6a6cd5db5e8f7e99e8606bcc.jpg",
                    "is_banned": "",
                    "is_repin": "",
                    "likes": "0",
                    "pin_join": "3d35891f6a6cd5db5e8f7e99e8606bcc",
                    "pinner": "280419651706424467",
                    "place": "",
                    "price": "64.95",
                    "price_currency": "USD",
                    "repins": "1",
                    "source": "http://www.etsy.com/listing/98147208/champagne-feather-flower-headpiece-set?ref=sr_gallery_32&ga_includes%5B0%5D=tags&ga_search_query=champagne+headpiece&ga_page=7&ga_search_type=all&ga_view_type=gallery",
                    "title": "Gettin' married",
                    "type": "pin",
                    "url": "https://www.pinterest.com/pin/280419514268559589/",
                    "via_pinner": ""
                },
                "_type": "pin"
            },
            {
                "_id": "108016091034794604",
                "_index": "pinterest",
                "_score": 0.53104424,
                "_source": {
                    "board": "108016159751668489",
                    "comment_count": "0",
                    "created": "Thu, 24 Jan 2013 20:00:11 +0000",
                    "description": "Darwin's Feather Collection - 25 Original Watercolor Feather Studies. $1,000.00, via Etsy.",
                    "domain": "etsy.com",
                    "id": "108016091034794604",
                    "image": "https://s-media-cache-ak0.pinimg.com/736x/da/88/cb/da88cbe64dab6d13895df95c18464a0c.jpg",
                    "image236": "https://s-media-cache-ak0.pinimg.com/236x/da/88/cb/da88cbe64dab6d13895df95c18464a0c.jpg",
                    "image60": "https://s-media-cache-ak0.pinimg.com/60x60/da/88/cb/da88cbe64dab6d13895df95c18464a0c.jpg",
                    "is_banned": "",
                    "is_repin": "",
                    "likes": "0",
                    "pin_join": "da88cbe64dab6d13895df95c18464a0c",
                    "pinner": "108016228471144513",
                    "place": "",
                    "price": "1000",
                    "price_currency": "USD",
                    "repins": "1",
                    "source": "http://www.etsy.com/listing/112653501/darwins-feather-collection-25-original?ref=sr_gallery_22&ga_search_query=watercolor&ga_view_type=gallery&ga_ship_to=US&ga_ref=auto2&ga_explicit_scope=1&ga_search_type=handmade",
                    "title": "Wall Art",
                    "type": "pin",
                    "url": "https://www.pinterest.com/pin/108016091034794604/",
                    "via_pinner": ""
                },
                "_type": "pin"
            },
            {
                "_id": "43628690111123201",
                "_index": "pinterest",
                "_score": 0.49254462,
                "_source": {
                    "board": "43628758829167857",
                    "comment_count": "0",
                    "created": "Mon, 06 Aug 2012 09:31:23 +0000",
                    "description": "Parisian Pink Feather Dress by BitsyButtercup on Etsy",
                    "domain": "etsy.com",
                    "id": "43628690111123201",
                    "image": "https://s-media-cache-ak0.pinimg.com/736x/b7/6f/a5/b76fa5056d2a5cbd94c1532ee5c328c8.jpg",
                    "image236": "https://s-media-cache-ak0.pinimg.com/236x/b7/6f/a5/b76fa5056d2a5cbd94c1532ee5c328c8.jpg",
                    "image60": "https://s-media-cache-ak0.pinimg.com/60x60/b7/6f/a5/b76fa5056d2a5cbd94c1532ee5c328c8.jpg",
                    "is_banned": "",
                    "is_repin": "",
                    "likes": "0",
                    "pin_join": "b76fa5056d2a5cbd94c1532ee5c328c8",
                    "pinner": "43628827548584315",
                    "place": "",
                    "price": "0",
                    "price_currency": "USD",
                    "repins": "3",
                    "source": "http://www.etsy.com/listing/105087625/parisian-pink-feather-dress?ref=cat_gallery_18",
                    "title": "Flower Girl",
                    "type": "pin",
                    "url": "https://www.pinterest.com/pin/43628690111123201/",
                    "via_pinner": ""
                },
                "_type": "pin"
            },
            {
                "_id": "197384396138295363",
                "_index": "pinterest",
                "_score": 0.47284043,
                "_source": {
                    "board": "197384464857330415",
                    "comment_count": "0",
                    "created": "Sat, 03 Mar 2012 20:44:53 +0000",
                    "description": "Vintage Peacock Feather Clutch Purse",
                    "domain": "etsy.com",
                    "id": "197384396138295363",
                    "image": "https://s-media-cache-ak0.pinimg.com/736x/5e/e3/81/5ee3815d00ea350497f03ad0f00fed24.jpg",
                    "image236": "https://s-media-cache-ak0.pinimg.com/236x/5e/e3/81/5ee3815d00ea350497f03ad0f00fed24.jpg",
                    "image60": "https://s-media-cache-ak0.pinimg.com/60x60/5e/e3/81/5ee3815d00ea350497f03ad0f00fed24.jpg",
                    "is_banned": "",
                    "is_repin": "1",
                    "likes": "0",
                    "pin_join": "",
                    "pinner": "197384533576780657",
                    "place": "",
                    "price": "0",
                    "price_currency": "USD",
                    "repins": "1",
                    "source": "http://www.etsy.com/listing/60761914/vintage-peacock-feather-clutch-purse",
                    "title": "Just for Ashley",
                    "type": "pin",
                    "url": "https://www.pinterest.com/pin/197384396138295363/",
                    "via_pinner": ""
                },
                "_type": "pin"
            },
            {
                "_id": "233342824412650727",
                "_index": "pinterest",
                "_score": 0.44457617,
                "_source": {
                    "board": "233342893132089854",
                    "comment_count": "0",
                    "created": "Thu, 08 Sep 2011 16:12:55 +0000",
                    "description": "Gold and purple Venetian feather carnival mask, Mauve by ladyinthetower on etsy",
                    "domain": "etsy.com",
                    "id": "233342824412650727",
                    "image": "https://s-media-cache-ak0.pinimg.com/736x/7b/fb/76/7bfb76e5c600a055c9ef5c8e80703fe4.jpg",
                    "image236": "https://s-media-cache-ak0.pinimg.com/236x/7b/fb/76/7bfb76e5c600a055c9ef5c8e80703fe4.jpg",
                    "image60": "https://s-media-cache-ak0.pinimg.com/60x60/7b/fb/76/7bfb76e5c600a055c9ef5c8e80703fe4.jpg",
                    "is_banned": "",
                    "is_repin": "",
                    "likes": "2",
                    "pin_join": "",
                    "pinner": "233342961851564311",
                    "place": "",
                    "price": "0",
                    "price_currency": "USD",
                    "repins": "22",
                    "source": "http://www.etsy.com/listing/66284302/gold-and-purple-venetian-feather",
                    "title": "Masks",
                    "type": "pin",
                    "url": "https://www.pinterest.com/pin/233342824412650727/",
                    "via_pinner": ""
                },
                "_type": "pin"
            },
            {
                "_id": "364650901048716531",
                "_index": "pinterest",
                "_score": 0.4313447,
                "_source": {
                    "board": "364650969767641011",
                    "comment_count": "0",
                    "created": "Tue, 12 Feb 2013 12:23:31 +0000",
                    "description": "Peg Fennimore - World Renowned Traditional Feather Painting Artist",
                    "domain": "pegsfeathers.com",
                    "id": "364650901048716531",
                    "image": "https://s-media-cache-ak0.pinimg.com/736x/f6/e6/26/f6e6263273df5f4c5fb63a97b7b2e948.jpg",
                    "image236": "https://s-media-cache-ak0.pinimg.com/236x/f6/e6/26/f6e6263273df5f4c5fb63a97b7b2e948.jpg",
                    "image60": "https://s-media-cache-ak0.pinimg.com/60x60/f6/e6/26/f6e6263273df5f4c5fb63a97b7b2e948.jpg",
                    "is_banned": "",
                    "is_repin": "",
                    "likes": "2",
                    "pin_join": "f6e6263273df5f4c5fb63a97b7b2e948",
                    "pinner": "364651038487092171",
                    "place": "",
                    "price": "0",
                    "price_currency": "USD",
                    "repins": "1",
                    "source": "http://www.pegsfeathers.com/feather-online-gallery.shtml",
                    "title": "plumas pintadas",
                    "type": "pin",
                    "url": "https://www.pinterest.com/pin/364650901048716531/",
                    "via_pinner": ""
                },
                "_type": "pin"
            },
            {
                "_id": "156289049539666270",
                "_index": "pinterest",
                "_score": 0.4277678,
                "_source": {
                    "board": "156289118257608574",
                    "comment_count": "0",
                    "created": "Mon, 03 Sep 2012 16:26:05 +0000",
                    "description": "Colourful Feather Earrings Price: \u00a34.00 #fashion #jewellery #earrings #feather",
                    "domain": "carolesgems.co.uk",
                    "id": "156289049539666270",
                    "image": "https://s-media-cache-ak0.pinimg.com/736x/ca/57/86/ca578695437f733b0b562328072014dc.jpg",
                    "image236": "https://s-media-cache-ak0.pinimg.com/236x/ca/57/86/ca578695437f733b0b562328072014dc.jpg",
                    "image60": "https://s-media-cache-ak0.pinimg.com/60x60/ca/57/86/ca578695437f733b0b562328072014dc.jpg",
                    "is_banned": "",
                    "is_repin": "",
                    "likes": "0",
                    "pin_join": "",
                    "pinner": "156289186977028087",
                    "place": "",
                    "price": "4",
                    "price_currency": "GBP",
                    "repins": "0",
                    "source": "http://www.carolesgems.co.uk/colourful-feather-earrings",
                    "title": "Earrings",
                    "type": "pin",
                    "url": "https://www.pinterest.com/pin/156289049539666270/",
                    "via_pinner": ""
                },
                "_type": "pin"
            },
            {
                "_id": "165999936236922344",
                "_index": "pinterest",
                "_score": 0.41986433,
                "_source": {
                    "board": "166000004954114575",
                    "comment_count": "0",
                    "created": "Sat, 22 Dec 2012 00:28:17 +0000",
                    "description": "feather-pen \u2764 liked on Polyvore",
                    "domain": "polyvore.com",
                    "id": "165999936236922344",
                    "image": "https://s-media-cache-ak0.pinimg.com/736x/4c/a1/1c/4ca11cdf4fec93f9021167f4ffe48e6c.jpg",
                    "image236": "https://s-media-cache-ak0.pinimg.com/236x/4c/a1/1c/4ca11cdf4fec93f9021167f4ffe48e6c.jpg",
                    "image60": "https://s-media-cache-ak0.pinimg.com/60x60/4c/a1/1c/4ca11cdf4fec93f9021167f4ffe48e6c.jpg",
                    "is_banned": "",
                    "is_repin": "1",
                    "likes": "0",
                    "pin_join": "4ca11cdf4fec93f9021167f4ffe48e6c",
                    "pinner": "166000073673545282",
                    "place": "",
                    "price": "0",
                    "price_currency": "USD",
                    "repins": "1",
                    "source": "http://www.polyvore.com/feather-pen/thing.outbound?.embedder=337389&.svc=pinterest&id=21731040",
                    "title": "My Style",
                    "type": "pin",
                    "url": "https://www.pinterest.com/pin/165999936236922344/",
                    "via_pinner": ""
                },
                "_type": "pin"
            },
            {
                "_id": "94364554667559299",
                "_index": "pinterest",
                "_score": 0.41780582,
                "_source": {
                    "board": "94364623381337502",
                    "comment_count": "0",
                    "created": "Wed, 13 Aug 2014 19:09:36 +0000",
                    "description": "Elegant Feather Flower Fascinator with Bird Cage Veil Comb or Clip in choice of white or ivory, Bride Hair Accessory, Wedding Hair Accessory...",
                    "domain": "etsy.com",
                    "id": "94364554667559299",
                    "image": "https://s-media-cache-ak0.pinimg.com/736x/83/18/9b/83189b9e8708ed6028b2735d0abc0818.jpg",
                    "image236": "https://s-media-cache-ak0.pinimg.com/236x/83/18/9b/83189b9e8708ed6028b2735d0abc0818.jpg",
                    "image60": "https://s-media-cache-ak0.pinimg.com/60x60/83/18/9b/83189b9e8708ed6028b2735d0abc0818.jpg",
                    "is_banned": "",
                    "is_repin": "",
                    "likes": "0",
                    "pin_join": "",
                    "pinner": "94364692100682394",
                    "place": "",
                    "price": "0",
                    "price_currency": "USD",
                    "repins": "2",
                    "source": "https://www.etsy.com/listing/198050018/elegant-feather-flower-fascinator-with?ref=br_feed_56&br_feed_tlp=weddings",
                    "title": "The bride",
                    "type": "pin",
                    "url": "https://www.pinterest.com/pin/94364554667559299/",
                    "via_pinner": ""
                },
                "_type": "pin"
            },
            {
                "_id": "115404809172416528",
                "_index": "pinterest",
                "_score": 0.4175644,
                "_source": {
                    "board": "115404877890380444",
                    "comment_count": "0",
                    "created": "Mon, 01 Oct 2012 16:11:18 +0000",
                    "description": "Ivory and Peacock Feather Bridal Hair Clip by TheHeadbandShoppe, $38.00",
                    "domain": "etsy.com",
                    "id": "115404809172416528",
                    "image": "https://s-media-cache-ak0.pinimg.com/736x/25/fc/35/25fc354627fea3e266ef5fe90b03d314.jpg",
                    "image236": "https://s-media-cache-ak0.pinimg.com/236x/25/fc/35/25fc354627fea3e266ef5fe90b03d314.jpg",
                    "image60": "https://s-media-cache-ak0.pinimg.com/60x60/25/fc/35/25fc354627fea3e266ef5fe90b03d314.jpg",
                    "is_banned": "",
                    "is_repin": "",
                    "likes": "0",
                    "pin_join": "25fc354627fea3e266ef5fe90b03d314",
                    "pinner": "115404946609801463",
                    "place": "",
                    "price": "38",
                    "price_currency": "USD",
                    "repins": "0",
                    "source": "http://www.etsy.com/listing/109098934/ivory-and-peacock-feather-bridal-hair?utm_source=Pinterest&utm_medium=PageTools&utm_campaign=Share",
                    "title": "welcome to my life",
                    "type": "pin",
                    "url": "https://www.pinterest.com/pin/115404809172416528/",
                    "via_pinner": ""
                },
                "_type": "pin"
            },
            {
                "_id": "240872280041084428",
                "_index": "pinterest",
                "_score": 0.3991129,
                "_source": {
                    "board": "240872348759132060",
                    "comment_count": "0",
                    "created": "Tue, 07 Aug 2012 01:43:16 +0000",
                    "description": "Silver Feather Pendent Earrings made in Canada by Links & Locks, $12.00",
                    "domain": "etsy.com",
                    "id": "240872280041084428",
                    "image": "https://s-media-cache-ak0.pinimg.com/736x/8c/50/3f/8c503f88370967d1ad336f78cd8b9870.jpg",
                    "image236": "https://s-media-cache-ak0.pinimg.com/236x/8c/50/3f/8c503f88370967d1ad336f78cd8b9870.jpg",
                    "image60": "https://s-media-cache-ak0.pinimg.com/60x60/8c/50/3f/8c503f88370967d1ad336f78cd8b9870.jpg",
                    "is_banned": "",
                    "is_repin": "",
                    "likes": "1",
                    "pin_join": "",
                    "pinner": "240872417478577263",
                    "place": "",
                    "price": "12",
                    "price_currency": "USD",
                    "repins": "3",
                    "source": "http://www.etsy.com/listing/106232633/silver-feather-pendent-earrings-made-in?utm_source=Pinterest&utm_medium=PageTools&utm_campaign=Share",
                    "title": "Links & Locks Jewellery ",
                    "type": "pin",
                    "url": "https://www.pinterest.com/pin/240872280041084428/",
                    "via_pinner": ""
                },
                "_type": "pin"
            },
            {
                "_id": "68679963041510781",
                "_index": "pinterest",
                "_score": 0.38686374,
                "_source": {
                    "board": "68680031756465870",
                    "comment_count": "0",
                    "created": "Fri, 17 Jan 2014 21:14:52 +0000",
                    "description": "Peacock Garter Set Peacock Fascinator Pink by NakedOrchidGarters, $146.99",
                    "domain": "etsy.com",
                    "id": "68679963041510781",
                    "image": "https://s-media-cache-ak0.pinimg.com/736x/e8/36/cc/e836cc53b4bc6d4c5bf67c9519dcc83c.jpg",
                    "image236": "https://s-media-cache-ak0.pinimg.com/236x/e8/36/cc/e836cc53b4bc6d4c5bf67c9519dcc83c.jpg",
                    "image60": "https://s-media-cache-ak0.pinimg.com/60x60/e8/36/cc/e836cc53b4bc6d4c5bf67c9519dcc83c.jpg",
                    "is_banned": "",
                    "is_repin": "",
                    "likes": "0",
                    "pin_join": "e836cc53b4bc6d4c5bf67c9519dcc83c",
                    "pinner": "68680100475834076",
                    "place": "",
                    "price": "146.99",
                    "price_currency": "USD",
                    "repins": "0",
                    "source": "http://www.etsy.com/listing/117156514/peacock-garter-set-peacock-fascinator?utm_source=Pinterest&utm_medium=PageTools&utm_campaign=Share",
                    "title": "Peacock Garter Set, Peacock Fascinator, Pink Prom Garter, Purple Zebra Garter, Peacock Hair Clip, Wedding Accessory, Pink Feather Garters",
                    "type": "pin",
                    "url": "https://www.pinterest.com/pin/68679963041510781/",
                    "via_pinner": ""
                },
                "_type": "pin"
            },
            {
                "_id": "493636809128913287",
                "_index": "pinterest",
                "_score": 0.3848301,
                "_source": {
                    "board": "493636877845338807",
                    "comment_count": "0",
                    "created": "Mon, 31 Mar 2014 01:02:24 +0000",
                    "description": "Red and Black Feather Bracelet by DarkInterior on Etsy, $9.00",
                    "domain": "etsy.com",
                    "id": "493636809128913287",
                    "image": "https://s-media-cache-ak0.pinimg.com/736x/37/8d/2c/378d2c9280a9694da7d91911855c0034.jpg",
                    "image236": "https://s-media-cache-ak0.pinimg.com/236x/37/8d/2c/378d2c9280a9694da7d91911855c0034.jpg",
                    "image60": "https://s-media-cache-ak0.pinimg.com/60x60/37/8d/2c/378d2c9280a9694da7d91911855c0034.jpg",
                    "is_banned": "",
                    "is_repin": "",
                    "likes": "0",
                    "pin_join": "378d2c9280a9694da7d91911855c0034",
                    "pinner": "493636946564759209",
                    "place": "",
                    "price": "9",
                    "price_currency": "USD",
                    "repins": "0",
                    "source": "https://www.etsy.com/listing/184520612/red-and-black-feather-bracelet?utm_source=Pinterest&utm_medium=PageTools&utm_campaign=Share",
                    "title": "Bracelets",
                    "type": "pin",
                    "url": "https://www.pinterest.com/pin/493636809128913287/",
                    "via_pinner": ""
                },
                "_type": "pin"
            },
            {
                "_id": "85005511686353038",
                "_index": "pinterest",
                "_score": 0.3847235,
                "_source": {
                    "board": "85005580405587134",
                    "comment_count": "0",
                    "created": "Mon, 16 Jan 2012 20:04:44 +0000",
                    "description": "Three Feather Car Dash Dream Catcher (Brown)    Hang the Reina Indian Summer Car Dash Dream Catcher on your car mirror to keep you and your car lookin\u2019 good. Features include 7 cm diameter metal hoop wrapped, turquoise chunk bead at center, and three sets of assorted feathers.  Measures approximately 6 inches while lying flat.",
                    "domain": "reinajewelry.com",
                    "id": "85005511686353038",
                    "image": "https://s-media-cache-ak0.pinimg.com/736x/4d/e3/89/4de389a787c7d868f9f2646107ad9864.jpg",
                    "image236": "https://s-media-cache-ak0.pinimg.com/236x/4d/e3/89/4de389a787c7d868f9f2646107ad9864.jpg",
                    "image60": "https://s-media-cache-ak0.pinimg.com/60x60/4d/e3/89/4de389a787c7d868f9f2646107ad9864.jpg",
                    "is_banned": "",
                    "is_repin": "",
                    "likes": "1",
                    "pin_join": "4de389a787c7d868f9f2646107ad9864",
                    "pinner": "85005649125050154",
                    "place": "",
                    "price": "0",
                    "price_currency": "USD",
                    "repins": "2",
                    "source": "http://www.reinajewelry.com/three-feather-car-dash-dream-catcher-brown/",
                    "title": "keep dreamin'",
                    "type": "pin",
                    "url": "https://www.pinterest.com/pin/85005511686353038/",
                    "via_pinner": ""
                },
                "_type": "pin"
            },
            {
                "_id": "26669822763785308",
                "_index": "pinterest",
                "_score": 0.37279212,
                "_source": {
                    "board": "26669891482335322",
                    "comment_count": "0",
                    "created": "Mon, 04 Jun 2012 20:15:37 +0000",
                    "description": "Another Jumper- yes!  This one is strapless, magenta top and black wide-legged bottom.  I added a black knit jacket for a nice stroll in NYC.  Easy Breezy....Yes indeed.  Jewelry: Long magenta/black Drake Anthony wire crochet and feather earrings/beaded bracelet and ring.  Shoe: black flip-flop  Hair: single braids twisted on both sides and pulled to the back.",
                    "domain": "Uploaded by user",
                    "id": "26669822763785308",
                    "image": "https://s-media-cache-ak0.pinimg.com/736x/f0/33/58/f03358f735d2b23522b6a43d76fe36a4.jpg",
                    "image236": "https://s-media-cache-ak0.pinimg.com/236x/f0/33/58/f03358f735d2b23522b6a43d76fe36a4.jpg",
                    "image60": "https://s-media-cache-ak0.pinimg.com/60x60/f0/33/58/f03358f735d2b23522b6a43d76fe36a4.jpg",
                    "is_banned": "",
                    "is_repin": "",
                    "likes": "2",
                    "pin_join": "f03358f735d2b23522b6a43d76fe36a4",
                    "pinner": "26669960201769275",
                    "place": "",
                    "price": "0",
                    "price_currency": "USD",
                    "repins": "1",
                    "source": "",
                    "title": "Style- My way",
                    "type": "pin",
                    "url": "https://www.pinterest.com/pin/26669822763785308/",
                    "via_pinner": ""
                },
                "_type": "pin"
            },
            {
                "_id": "485544403548747798",
                "_index": "pinterest",
                "_score": 0.36840692,
                "_source": {
                    "board": "485544472264950584",
                    "comment_count": "0",
                    "created": "Mon, 14 Apr 2014 00:40:30 +0000",
                    "description": "Vintage Millinery Rust Brown Feather Ostrich Plume Felt Union Made USA RARE FUNKY Hat.  We are TOP RATED Power Sellers on Ebay at 4COOLSTUFF2BUY.",
                    "domain": "r.ebay.com",
                    "id": "485544403548747798",
                    "image": "https://s-media-cache-ak0.pinimg.com/736x/ed/ba/78/edba78c2889d6c0c383dfe95b7b95238.jpg",
                    "image236": "https://s-media-cache-ak0.pinimg.com/236x/ed/ba/78/edba78c2889d6c0c383dfe95b7b95238.jpg",
                    "image60": "https://s-media-cache-ak0.pinimg.com/60x60/ed/ba/78/edba78c2889d6c0c383dfe95b7b95238.jpg",
                    "is_banned": "",
                    "is_repin": "1",
                    "likes": "0",
                    "pin_join": "edba78c2889d6c0c383dfe95b7b95238",
                    "pinner": "485544540984317239",
                    "place": "",
                    "price": "0",
                    "price_currency": "USD",
                    "repins": "0",
                    "source": "http://r.ebay.com/pRqBAS",
                    "title": "Vtg Millinery Rust Feather Ostrich Plume Felt Union Made USA RARE FUNKY Hat COOL",
                    "type": "pin",
                    "url": "https://www.pinterest.com/pin/485544403548747798/",
                    "via_pinner": ""
                },
                "_type": "pin"
            },
            {
                "_id": "47428602295440727",
                "_index": "pinterest",
                "_score": 0.3681758,
                "_source": {
                    "board": "47428671014713187",
                    "comment_count": "0",
                    "created": "Mon, 12 Dec 2011 16:47:07 +0000",
                    "description": "ostrich feather earring",
                    "domain": "greenteadesign.com",
                    "id": "47428602295440727",
                    "image": "https://s-media-cache-ak0.pinimg.com/736x/9e/39/9b/9e399b2379ad336377b41a8bac8c0f94.jpg",
                    "image236": "https://s-media-cache-ak0.pinimg.com/236x/9e/39/9b/9e399b2379ad336377b41a8bac8c0f94.jpg",
                    "image60": "https://s-media-cache-ak0.pinimg.com/60x60/9e/39/9b/9e399b2379ad336377b41a8bac8c0f94.jpg",
                    "is_banned": "",
                    "is_repin": "",
                    "likes": "0",
                    "pin_join": "",
                    "pinner": "47428739734175816",
                    "place": "",
                    "price": "0",
                    "price_currency": "USD",
                    "repins": "6",
                    "source": "http://www.greenteadesign.com/thedesigntree/fashion/no-burying-your-head-in-the-sand-the-ostrich%E2%80%99s-gifts/",
                    "title": "jewelry and accessories",
                    "type": "pin",
                    "url": "https://www.pinterest.com/pin/47428602295440727/",
                    "via_pinner": ""
                },
                "_type": "pin"
            },
            {
                "_id": "561331541024999609",
                "_index": "pinterest",
                "_score": 0.35619208,
                "_source": {
                    "board": "561331609744192391",
                    "comment_count": "0",
                    "created": "Thu, 13 Dec 2012 03:15:02 +0000",
                    "description": "This would be a fun look for a flower girl - flowers/feather headband and pearls :)",
                    "domain": "etsy.com",
                    "id": "561331541024999609",
                    "image": "https://s-media-cache-ak0.pinimg.com/736x/14/2d/75/142d750d704b1f9c5e605d809a39d5e0.jpg",
                    "image236": "https://s-media-cache-ak0.pinimg.com/236x/14/2d/75/142d750d704b1f9c5e605d809a39d5e0.jpg",
                    "image60": "https://s-media-cache-ak0.pinimg.com/60x60/14/2d/75/142d750d704b1f9c5e605d809a39d5e0.jpg",
                    "is_banned": "",
                    "is_repin": "1",
                    "likes": "0",
                    "pin_join": "",
                    "pinner": "561331678463659424",
                    "place": "",
                    "price": "0",
                    "price_currency": "USD",
                    "repins": "0",
                    "source": "http://www.etsy.com/listing/88717652/vintage-silk-rosettes-ostrich-feather?utm_source=Pinterest&utm_medium=PageTools&utm_campaign=Share",
                    "title": "Beauty",
                    "type": "pin",
                    "url": "https://www.pinterest.com/pin/561331541024999609/",
                    "via_pinner": ""
                },
                "_type": "pin"
            },
            {
                "_id": "218987600605178819",
                "_index": "pinterest",
                "_score": 0.3534927,
                "_source": {
                    "board": "218987669319894144",
                    "comment_count": "0",
                    "created": "Fri, 25 Oct 2013 16:32:20 +0000",
                    "description": "ROMWE | Purple Faux Feather Skirt, The Latest Street Fashion - this is perfect in so many ways! Gorgeous <3 it!!! Need!!! #fashion #streetstyle",
                    "domain": "romwe.com",
                    "id": "218987600605178819",
                    "image": "https://s-media-cache-ak0.pinimg.com/736x/04/ca/db/04cadbe40caa6b05ecdefc59d9f47980.jpg",
                    "image236": "https://s-media-cache-ak0.pinimg.com/236x/04/ca/db/04cadbe40caa6b05ecdefc59d9f47980.jpg",
                    "image60": "https://s-media-cache-ak0.pinimg.com/60x60/04/ca/db/04cadbe40caa6b05ecdefc59d9f47980.jpg",
                    "is_banned": "",
                    "is_repin": "1",
                    "likes": "6",
                    "pin_join": "",
                    "pinner": "12173998901170277",
                    "place": "",
                    "price": "0",
                    "price_currency": "USD",
                    "repins": "36",
                    "source": "http://www.romwe.com/purple-faux-feather-skirt-p-76687.html?Pinterest=kekekapan",
                    "title": "::::::::::Fashion & Style::::::::::",
                    "type": "pin",
                    "url": "https://www.pinterest.com/pin/218987600605178819/",
                    "via_pinner": "12173998901170277"
                },
                "_type": "pin"
            },
            {
                "_id": "14355292535174923",
                "_index": "pinterest",
                "_score": 0.35176817,
                "_source": {
                    "board": "14355361251286643",
                    "comment_count": "0",
                    "created": "Fri, 28 Jun 2013 02:53:28 +0000",
                    "description": "FRencH CoTTage PiLLow 18\" PaRiS  DesiGN PriNT SHaBBy ChiC ReD TiCKing on Etsy, $39.00",
                    "domain": "etsy.com",
                    "id": "14355292535174923",
                    "image": "https://s-media-cache-ak0.pinimg.com/736x/6d/21/a1/6d21a12588d0b8a6584576390323d7f4.jpg",
                    "image236": "https://s-media-cache-ak0.pinimg.com/236x/6d/21/a1/6d21a12588d0b8a6584576390323d7f4.jpg",
                    "image60": "https://s-media-cache-ak0.pinimg.com/60x60/6d/21/a1/6d21a12588d0b8a6584576390323d7f4.jpg",
                    "is_banned": "",
                    "is_repin": "",
                    "likes": "1",
                    "pin_join": "6d21a12588d0b8a6584576390323d7f4",
                    "pinner": "14355429970674710",
                    "place": "",
                    "price": "39",
                    "price_currency": "USD",
                    "repins": "3",
                    "source": "http://www.etsy.com/listing/110014449/french-cottage-pillow-18-paris-design",
                    "title": "FRencH CoTTage PiLLow 18\" DOWN FEATHER PaRiS DesiGN PriNT SHaBBy ChiC ReD TiCKing",
                    "type": "pin",
                    "url": "https://www.pinterest.com/pin/14355292535174923/",
                    "via_pinner": ""
                },
                "_type": "pin"
            },
            {
                "_id": "218072806927958916",
                "_index": "pinterest",
                "_score": 0.35066667,
                "_source": {
                    "board": "218072875645556334",
                    "comment_count": "0",
                    "created": "Tue, 23 Oct 2012 00:08:20 +0000",
                    "description": ".",
                    "domain": "etsy.com",
                    "id": "218072806927958916",
                    "image": "https://s-media-cache-ak0.pinimg.com/736x/84/2a/02/842a027cf5d978c4e8f8790282135984.jpg",
                    "image236": "https://s-media-cache-ak0.pinimg.com/236x/84/2a/02/842a027cf5d978c4e8f8790282135984.jpg",
                    "image60": "https://s-media-cache-ak0.pinimg.com/60x60/84/2a/02/842a027cf5d978c4e8f8790282135984.jpg",
                    "is_banned": "",
                    "is_repin": "",
                    "likes": "0",
                    "pin_join": "842a027cf5d978c4e8f8790282135984",
                    "pinner": "218072944365013193",
                    "place": "",
                    "price": "0",
                    "price_currency": "USD",
                    "repins": "0",
                    "source": "http://www.etsy.com/listing/104910292/45-off-fall-sale-feather-rose-flower",
                    "title": "Feather Rose Flower Headband - Shabby Headband - Baby Headband - Toddler Headband",
                    "type": "pin",
                    "url": "https://www.pinterest.com/pin/218072806927958916/",
                    "via_pinner": ""
                },
                "_type": "pin"
            },
            {
                "_id": "402368547927908529",
                "_index": "pinterest",
                "_score": 0.34586433,
                "_source": {
                    "board": "402368616647087802",
                    "comment_count": "0",
                    "created": "Thu, 14 Feb 2013 17:00:12 +0000",
                    "description": "Brown and Green Beaded Feather Earrings, $3.99",
                    "domain": "goodsmiths.com",
                    "id": "402368547927908529",
                    "image": "https://s-media-cache-ak0.pinimg.com/736x/55/43/73/55437323a347786be7652823ed6722a0.jpg",
                    "image236": "https://s-media-cache-ak0.pinimg.com/236x/55/43/73/55437323a347786be7652823ed6722a0.jpg",
                    "image60": "https://s-media-cache-ak0.pinimg.com/60x60/55/43/73/55437323a347786be7652823ed6722a0.jpg",
                    "is_banned": "",
                    "is_repin": "",
                    "likes": "0",
                    "pin_join": "55437323a347786be7652823ed6722a0",
                    "pinner": "402368685366318715",
                    "place": "",
                    "price": "3.99",
                    "price_currency": "USD",
                    "repins": "0",
                    "source": "https://www.goodsmiths.com/l/843ef0",
                    "title": "FEATHER EARRINGS",
                    "type": "pin",
                    "url": "https://www.pinterest.com/pin/402368547927908529/",
                    "via_pinner": ""
                },
                "_type": "pin"
            },
            {
                "_id": "43910165088089728",
                "_index": "pinterest",
                "_score": 0.34466743,
                "_source": {
                    "board": "43910233805841714",
                    "comment_count": "0",
                    "created": "Tue, 02 Oct 2012 00:15:59 +0000",
                    "description": "Chargers Feather Bottle Cap Hair Clip or by wisteriahousewife, $9.99",
                    "domain": "etsy.com",
                    "id": "43910165088089728",
                    "image": "https://s-media-cache-ak0.pinimg.com/736x/dd/aa/93/ddaa93ed20b6d275eb3d2a94af83d3f4.jpg",
                    "image236": "https://s-media-cache-ak0.pinimg.com/236x/dd/aa/93/ddaa93ed20b6d275eb3d2a94af83d3f4.jpg",
                    "image60": "https://s-media-cache-ak0.pinimg.com/60x60/dd/aa/93/ddaa93ed20b6d275eb3d2a94af83d3f4.jpg",
                    "is_banned": "",
                    "is_repin": "",
                    "likes": "1",
                    "pin_join": "",
                    "pinner": "43910302525294455",
                    "place": "",
                    "price": "9.99",
                    "price_currency": "USD",
                    "repins": "0",
                    "source": "http://www.etsy.com/listing/110990652/chargers-feather-bottle-cap-hair-clip-or?utm_source=Pinterest&utm_medium=PageTools&utm_campaign=Share",
                    "title": "Wisteria Housewife",
                    "type": "pin",
                    "url": "https://www.pinterest.com/pin/43910165088089728/",
                    "via_pinner": ""
                },
                "_type": "pin"
            },
            {
                "_id": "52002570668023172",
                "_index": "pinterest",
                "_score": 0.3417413,
                "_source": {
                    "board": "52002639386293770",
                    "comment_count": "0",
                    "created": "Sun, 22 Jul 2012 03:03:15 +0000",
                    "description": "Peacock Feather Filled Glass Bottle Earrings",
                    "domain": "wanelo.com",
                    "id": "52002570668023172",
                    "image": "https://s-media-cache-ak0.pinimg.com/736x/cb/a3/40/cba3402e4927b149d555f3254f1a87d0.jpg",
                    "image236": "https://s-media-cache-ak0.pinimg.com/236x/cb/a3/40/cba3402e4927b149d555f3254f1a87d0.jpg",
                    "image60": "https://s-media-cache-ak0.pinimg.com/60x60/cb/a3/40/cba3402e4927b149d555f3254f1a87d0.jpg",
                    "is_banned": "",
                    "is_repin": "",
                    "likes": "0",
                    "pin_join": "",
                    "pinner": "52002708105729094",
                    "place": "",
                    "price": "0",
                    "price_currency": "USD",
                    "repins": "1",
                    "source": "http://wanelo.com/p/1595514/peacock-feather-filled-glass-bottle-earrings",
                    "title": "Jewelry",
                    "type": "pin",
                    "url": "https://www.pinterest.com/pin/52002570668023172/",
                    "via_pinner": ""
                },
                "_type": "pin"
            },
            {
                "_id": "8585055514182271",
                "_index": "pinterest",
                "_score": 0.33473212,
                "_source": {
                    "board": "8585124228693504",
                    "comment_count": "0",
                    "created": "Sun, 06 Apr 2014 00:36:59 +0000",
                    "description": "Peacock Pocketfold wedding invitation, peacock feather wedding invitation, pocket fold invitation, ivory, teal, blue invitation on Etsy, $5.95",
                    "domain": "etsy.com",
                    "id": "8585055514182271",
                    "image": "https://s-media-cache-ak0.pinimg.com/736x/af/0a/03/af0a03a71311bec169d428cb2a0073c4.jpg",
                    "image236": "https://s-media-cache-ak0.pinimg.com/236x/af/0a/03/af0a03a71311bec169d428cb2a0073c4.jpg",
                    "image60": "https://s-media-cache-ak0.pinimg.com/60x60/af/0a/03/af0a03a71311bec169d428cb2a0073c4.jpg",
                    "is_banned": "",
                    "is_repin": "",
                    "likes": "0",
                    "pin_join": "af0a03a71311bec169d428cb2a0073c4",
                    "pinner": "8585192948111190",
                    "place": "",
                    "price": "5.95",
                    "price_currency": "USD",
                    "repins": "0",
                    "source": "https://www.etsy.com/listing/62053606/peacock-pocketfold-wedding-invitation",
                    "title": "Wedding stuff",
                    "type": "pin",
                    "url": "https://www.pinterest.com/pin/8585055514182271/",
                    "via_pinner": ""
                },
                "_type": "pin"
            },
            {
                "_id": "443112050806253284",
                "_index": "pinterest",
                "_score": 0.33197454,
                "_source": {
                    "board": "443112119525706799",
                    "comment_count": "0",
                    "created": "Sun, 02 Sep 2012 14:51:27 +0000",
                    "description": "Minimalist Feather Earrings Bright Red on #RebelsMarket",
                    "domain": "rebelsmarket.com",
                    "id": "443112050806253284",
                    "image": "https://s-media-cache-ak0.pinimg.com/736x/da/76/d9/da76d9f9172e0d5ffb2aa6f26d232be0.jpg",
                    "image236": "https://s-media-cache-ak0.pinimg.com/236x/da/76/d9/da76d9f9172e0d5ffb2aa6f26d232be0.jpg",
                    "image60": "https://s-media-cache-ak0.pinimg.com/60x60/da/76/d9/da76d9f9172e0d5ffb2aa6f26d232be0.jpg",
                    "is_banned": "",
                    "is_repin": "",
                    "likes": "0",
                    "pin_join": "",
                    "pinner": "443112188245180640",
                    "place": "",
                    "price": "0",
                    "price_currency": "USD",
                    "repins": "0",
                    "source": "http://www.rebelsmarket.com/products/minimalist-feather-earrings-bright-red-2135",
                    "title": "Still Tree Jewellery",
                    "type": "pin",
                    "url": "https://www.pinterest.com/pin/443112050806253284/",
                    "via_pinner": ""
                },
                "_type": "pin"
            },
            {
                "_id": "509962357777164431",
                "_index": "pinterest",
                "_score": 0.32918757,
                "_source": {
                    "board": "509962426494568187",
                    "comment_count": "0",
                    "created": "Sat, 07 Dec 2013 15:48:53 +0000",
                    "description": "Elizabethan Bride \u00a3190.00 The fabulous rosette dress is made in yummy hues of rich ivory and dusty rose, the top of the bodice features luxurious satin rosette material, and features and adjustable satin ribbon tie back.   The waistline boasts an adjustable satin sash featuring a luxurious beaded applique. The bottom half of this custom design features six layers of tulle, and is lined with striking maribou and chandelle feathers.",
                    "domain": "mytutuboutique.com",
                    "id": "509962357777164431",
                    "image": "https://s-media-cache-ak0.pinimg.com/736x/2d/cb/69/2dcb6998e227c95a3ff34bc81a9d2310.jpg",
                    "image236": "https://s-media-cache-ak0.pinimg.com/236x/2d/cb/69/2dcb6998e227c95a3ff34bc81a9d2310.jpg",
                    "image60": "https://s-media-cache-ak0.pinimg.com/60x60/2d/cb/69/2dcb6998e227c95a3ff34bc81a9d2310.jpg",
                    "is_banned": "",
                    "is_repin": "",
                    "likes": "0",
                    "pin_join": "",
                    "pinner": "509962495213976127",
                    "place": "",
                    "price": "190",
                    "price_currency": "GBP",
                    "repins": "1",
                    "source": "http://www.mytutuboutique.com/i_3147/Elizabethan-Satin-Rosette-Feather-Tutu-Dress-with-Beaded-Sash.htm",
                    "title": "Party Couture",
                    "type": "pin",
                    "url": "https://www.pinterest.com/pin/509962357777164431/",
                    "via_pinner": ""
                },
                "_type": "pin"
            },
            {
                "_id": "174092341815453476",
                "_index": "pinterest",
                "_score": 0.32826093,
                "_source": {
                    "board": "174092410534520617",
                    "comment_count": "0",
                    "created": "Tue, 21 Feb 2012 15:29:42 +0000",
                    "description": "clip-in grizzly feather extensions",
                    "domain": "myprincessories.com",
                    "id": "174092341815453476",
                    "image": "https://s-media-cache-ak0.pinimg.com/736x/a3/2f/e1/a32fe17105a64432fee7f8f2b9c2fcbc.jpg",
                    "image236": "https://s-media-cache-ak0.pinimg.com/236x/a3/2f/e1/a32fe17105a64432fee7f8f2b9c2fcbc.jpg",
                    "image60": "https://s-media-cache-ak0.pinimg.com/60x60/a3/2f/e1/a32fe17105a64432fee7f8f2b9c2fcbc.jpg",
                    "is_banned": "",
                    "is_repin": "",
                    "likes": "0",
                    "pin_join": "a32fe17105a64432fee7f8f2b9c2fcbc",
                    "pinner": "174092479253973996",
                    "place": "",
                    "price": "0",
                    "price_currency": "USD",
                    "repins": "1",
                    "source": "http://myprincessories.com/item_533/Feather-Extensions.htm",
                    "title": "Accessories/Gifts/DIY Crafts",
                    "type": "pin",
                    "url": "https://www.pinterest.com/pin/174092341815453476/",
                    "via_pinner": ""
                },
                "_type": "pin"
            },
            {
                "_id": "253960866459866288",
                "_index": "pinterest",
                "_score": 0.32646078,
                "_source": {
                    "board": "253960935176150760",
                    "comment_count": "0",
                    "created": "Sun, 12 May 2013 09:36:15 +0000",
                    "description": "",
                    "domain": "etsy.com",
                    "id": "253960866459866288",
                    "image": "https://s-media-cache-ak0.pinimg.com/736x/a0/46/2c/a0462c302615093c93360a6763504c20.jpg",
                    "image236": "https://s-media-cache-ak0.pinimg.com/236x/a0/46/2c/a0462c302615093c93360a6763504c20.jpg",
                    "image60": "https://s-media-cache-ak0.pinimg.com/60x60/a0/46/2c/a0462c302615093c93360a6763504c20.jpg",
                    "is_banned": "",
                    "is_repin": "",
                    "likes": "0",
                    "pin_join": "a0462c302615093c93360a6763504c20",
                    "pinner": "253961003895620481",
                    "place": "",
                    "price": "0",
                    "price_currency": "USD",
                    "repins": "0",
                    "source": "http://www.etsy.com/listing/129878562/my-tribe-feather-cuff-bracelet?ref=shop_home_active",
                    "title": "My Tribe Feather Cuff Bracelet",
                    "type": "pin",
                    "url": "https://www.pinterest.com/pin/253960866459866288/",
                    "via_pinner": ""
                },
                "_type": "pin"
            },
            {
                "_id": "11259067788236560",
                "_index": "pinterest",
                "_score": 0.3235897,
                "_source": {
                    "board": "11259136507398480",
                    "comment_count": "0",
                    "created": "Sat, 28 Jan 2012 19:07:29 +0000",
                    "description": "Ivory Peacock Feather Shoe Clips  JAM by LookingGlassCouture, $36.00",
                    "domain": "etsy.com",
                    "id": "11259067788236560",
                    "image": "https://s-media-cache-ak0.pinimg.com/736x/72/8f/37/728f3721e9f8a956be7cfd1cae52a408.jpg",
                    "image236": "https://s-media-cache-ak0.pinimg.com/236x/72/8f/37/728f3721e9f8a956be7cfd1cae52a408.jpg",
                    "image60": "https://s-media-cache-ak0.pinimg.com/60x60/72/8f/37/728f3721e9f8a956be7cfd1cae52a408.jpg",
                    "is_banned": "",
                    "is_repin": "",
                    "likes": "0",
                    "pin_join": "728f3721e9f8a956be7cfd1cae52a408",
                    "pinner": "11259205226858340",
                    "place": "",
                    "price": "36",
                    "price_currency": "USD",
                    "repins": "0",
                    "source": "http://www.etsy.com/listing/83413146/ivory-peacock-feather-shoe-clips-jam?utm_source=Pinterest&utm_medium=PageTools&utm_campaign=Share",
                    "title": "Peacock",
                    "type": "pin",
                    "url": "https://www.pinterest.com/pin/11259067788236560/",
                    "via_pinner": ""
                },
                "_type": "pin"
            },
            {
                "_id": "119767671310364601",
                "_index": "pinterest",
                "_score": 0.32100973,
                "_source": {
                    "board": "119767740029365331",
                    "comment_count": "0",
                    "created": "Tue, 28 Feb 2012 15:46:45 +0000",
                    "description": "Disney Bridal Style 210 - Ariel Cascading ruffles in taffeta and satin organza pay tribute to Ariel\u2019s oceanic home. Inspired by the gentle movement of the ocean\u2019s tide, this romantic gown features gently cascading ruffles, self-made flowers with feather accents that softly sway and dance as if under the sea. The gown's one shoulder bodice is perfect for the bride who wants a splash of the unexpected.  I want this dress for my wedding because Ariel is my favorite Disney princesses and I want a fairy tale wedding! \ud83d\udc97",
                    "domain": "Uploaded by user",
                    "id": "119767671310364601",
                    "image": "https://s-media-cache-ak0.pinimg.com/736x/b5/80/63/b58063b43157e9715085c619eba08164.jpg",
                    "image236": "https://s-media-cache-ak0.pinimg.com/236x/b5/80/63/b58063b43157e9715085c619eba08164.jpg",
                    "image60": "https://s-media-cache-ak0.pinimg.com/60x60/b5/80/63/b58063b43157e9715085c619eba08164.jpg",
                    "is_banned": "",
                    "is_repin": "",
                    "likes": "7",
                    "pin_join": "",
                    "pinner": "119767808748817664",
                    "place": "",
                    "price": "0",
                    "price_currency": "USD",
                    "repins": "10",
                    "source": "None",
                    "title": "Wedding of My Dreams",
                    "type": "pin",
                    "url": "https://www.pinterest.com/pin/119767671310364601/",
                    "via_pinner": ""
                },
                "_type": "pin"
            },
            {
                "_id": "219620919300293653",
                "_index": "pinterest",
                "_score": 0.3188896,
                "_source": {
                    "board": "219620988017465109",
                    "comment_count": "0",
                    "created": "Mon, 31 Dec 2012 13:55:44 +0000",
                    "description": "Blue and yellow feather terrarium necklace by TheLittleBrokenWing, $22.00",
                    "domain": "etsy.com",
                    "id": "219620919300293653",
                    "image": "https://s-media-cache-ak0.pinimg.com/736x/32/f1/4d/32f14d369feb53b596a72d26cc78b6b0.jpg",
                    "image236": "https://s-media-cache-ak0.pinimg.com/236x/32/f1/4d/32f14d369feb53b596a72d26cc78b6b0.jpg",
                    "image60": "https://s-media-cache-ak0.pinimg.com/60x60/32/f1/4d/32f14d369feb53b596a72d26cc78b6b0.jpg",
                    "is_banned": "",
                    "is_repin": "",
                    "likes": "1",
                    "pin_join": "",
                    "pinner": "219621056736922186",
                    "place": "",
                    "price": "22",
                    "price_currency": "USD",
                    "repins": "1",
                    "source": "http://www.etsy.com/listing/118894563/blue-and-yellow-feather-terrarium?utm_source=Pinterest&utm_medium=PageTools&utm_campaign=Share",
                    "title": "Handmade by Me",
                    "type": "pin",
                    "url": "https://www.pinterest.com/pin/219620919300293653/",
                    "via_pinner": ""
                },
                "_type": "pin"
            },
            {
                "_id": "213569207301631298",
                "_index": "pinterest",
                "_score": 0.31834778,
                "_source": {
                    "board": "213569276018199996",
                    "comment_count": "0",
                    "created": "Sat, 30 Mar 2013 11:56:42 +0000",
                    "description": "Peacock feather hobo",
                    "domain": "Uploaded by user",
                    "id": "213569207301631298",
                    "image": "https://s-media-cache-ak0.pinimg.com/736x/a3/08/ce/a308ce9ae050968696d664935a9803ec.jpg",
                    "image236": "https://s-media-cache-ak0.pinimg.com/236x/a3/08/ce/a308ce9ae050968696d664935a9803ec.jpg",
                    "image60": "https://s-media-cache-ak0.pinimg.com/60x60/a3/08/ce/a308ce9ae050968696d664935a9803ec.jpg",
                    "is_banned": "",
                    "is_repin": "1",
                    "likes": "0",
                    "pin_join": "a308ce9ae050968696d664935a9803ec",
                    "pinner": "213569344737643824",
                    "place": "",
                    "price": "0",
                    "price_currency": "USD",
                    "repins": "0",
                    "source": "",
                    "title": "CLOTHES!",
                    "type": "pin",
                    "url": "https://www.pinterest.com/pin/213569207301631298/",
                    "via_pinner": ""
                },
                "_type": "pin"
            },
            {
                "_id": "99782947967225473",
                "_index": "pinterest",
                "_score": 0.31669107,
                "_source": {
                    "board": "99783016682918806",
                    "comment_count": "0",
                    "created": "Mon, 29 Jul 2013 12:58:09 +0000",
                    "description": "Native American Feather Style Hair Clip \"Protection\". Beautiful and hand made for summer accessories.",
                    "domain": "tahoebluedesigns.com",
                    "id": "99782947967225473",
                    "image": "https://s-media-cache-ak0.pinimg.com/736x/ec/7e/cd/ec7ecdc1273ed0ffd74481794aa03738.jpg",
                    "image236": "https://s-media-cache-ak0.pinimg.com/236x/ec/7e/cd/ec7ecdc1273ed0ffd74481794aa03738.jpg",
                    "image60": "https://s-media-cache-ak0.pinimg.com/60x60/ec/7e/cd/ec7ecdc1273ed0ffd74481794aa03738.jpg",
                    "is_banned": "",
                    "is_repin": "",
                    "likes": "0",
                    "pin_join": "",
                    "pinner": "171981416928645101",
                    "place": "",
                    "price": "0",
                    "price_currency": "USD",
                    "repins": "2",
                    "source": "http://www.tahoebluedesigns.com/?deeplink_referrer=socialB_pinterest#!product/prd1/991481594/native-american-feather-style-hair-clip-protection",
                    "title": "Items For Sale",
                    "type": "pin",
                    "url": "https://www.pinterest.com/pin/99782947967225473/",
                    "via_pinner": ""
                },
                "_type": "pin"
            },
            {
                "_id": "65865213273147492",
                "_index": "pinterest",
                "_score": 0.31535676,
                "_source": {
                    "board": "65865281989314952",
                    "comment_count": "0",
                    "created": "Tue, 07 May 2013 04:15:58 +0000",
                    "description": "Handwoven Gypsy Dreamcatcher Feather Purse Charm by TurquoiseCrush, $20.00",
                    "domain": "etsy.com",
                    "id": "65865213273147492",
                    "image": "https://s-media-cache-ak0.pinimg.com/736x/8f/6e/1b/8f6e1b9e5c7ed54702ebff572812de64.jpg",
                    "image236": "https://s-media-cache-ak0.pinimg.com/236x/8f/6e/1b/8f6e1b9e5c7ed54702ebff572812de64.jpg",
                    "image60": "https://s-media-cache-ak0.pinimg.com/60x60/8f/6e/1b/8f6e1b9e5c7ed54702ebff572812de64.jpg",
                    "is_banned": "",
                    "is_repin": "",
                    "likes": "0",
                    "pin_join": "8f6e1b9e5c7ed54702ebff572812de64",
                    "pinner": "65865350708729773",
                    "place": "",
                    "price": "20",
                    "price_currency": "USD",
                    "repins": "0",
                    "source": "http://www.etsy.com/listing/101607326/handwoven-gypsy-dreamcatcher-feather?utm_source=Pinterest&utm_medium=PageTools&utm_campaign=Share",
                    "title": "Accessories I love",
                    "type": "pin",
                    "url": "https://www.pinterest.com/pin/65865213273147492/",
                    "via_pinner": ""
                },
                "_type": "pin"
            },
            {
                "_id": "12947917652809964",
                "_index": "pinterest",
                "_score": 0.31452274,
                "_source": {
                    "board": "12947986367792920",
                    "comment_count": "0",
                    "created": "Tue, 14 Jan 2014 01:58:33 +0000",
                    "description": "Feather River Doors Preston Zinc Craftsman Primed Smooth Fiberglass Entry Door with Sidelites-A42101-3A4 at The Home Depot",
                    "domain": "homedepot.com",
                    "id": "12947917652809964",
                    "image": "https://s-media-cache-ak0.pinimg.com/736x/ee/a2/12/eea21223a256c6db10215042e9248894.jpg",
                    "image236": "https://s-media-cache-ak0.pinimg.com/236x/ee/a2/12/eea21223a256c6db10215042e9248894.jpg",
                    "image60": "https://s-media-cache-ak0.pinimg.com/60x60/ee/a2/12/eea21223a256c6db10215042e9248894.jpg",
                    "is_banned": "",
                    "is_repin": "",
                    "likes": "0",
                    "pin_join": "",
                    "pinner": "12948055087120911",
                    "place": "",
                    "price": "0",
                    "price_currency": "USD",
                    "repins": "0",
                    "source": "http://www.homedepot.com/p/Feather-River-Doors-Preston-Zinc-Craftsman-Primed-Smooth-Fiberglass-Entry-Door-with-Sidelites-A42101-3A4/202959954?N=ar90Z7cm%3Frpp%3D96",
                    "title": "For Our First Home",
                    "type": "pin",
                    "url": "https://www.pinterest.com/pin/12947917652809964/",
                    "via_pinner": ""
                },
                "_type": "pin"
            }
        ],
        "max_score": 1.0078546,
        "total": 184412
    },
    "timed_out": false,
    "took": 468
}
