{
    "_shards": {
        "failed": 0,
        "successful": 5,
        "total": 5
    },
    "hits": {
        "hits": [
            {
                "_id": "304907837243541263",
                "_index": "pinterest",
                "_score": 1.6194504,
                "_source": {
                    "board": "304907905960771861",
                    "comment_count": "0",
                    "created": "Mon, 23 Dec 2013 02:44:59 +0000",
                    "description": "20% OFF Unique Green Vintage Window Frame by AsIsRepurposedItems  This vintage deep green window frame is a beautiful addition to any room. The paint and wood on the frame have been left as is, to leave the authentic wear and tear for a chic finish.  www.asisrepurposeditems.com",
                    "domain": "etsy.com",
                    "id": "304907837243541263",
                    "image": "https://s-media-cache-ak0.pinimg.com/736x/21/6e/c3/216ec378c226a13aabfd9e1bbfcc2e7c.jpg",
                    "image236": "https://s-media-cache-ak0.pinimg.com/236x/21/6e/c3/216ec378c226a13aabfd9e1bbfcc2e7c.jpg",
                    "image60": "https://s-media-cache-ak0.pinimg.com/60x60/21/6e/c3/216ec378c226a13aabfd9e1bbfcc2e7c.jpg",
                    "is_banned": "",
                    "is_repin": "",
                    "likes": "0",
                    "pin_join": "",
                    "pinner": "304907974680248384",
                    "place": "",
                    "price": "0",
                    "price_currency": "USD",
                    "repins": "0",
                    "source": "https://www.etsy.com/listing/165200076/20-off-unique-green-vintage-window-frame?ref=related-2",
                    "title": "Unique Green Vintage Window Frame Mirror",
                    "type": "pin",
                    "url": "https://www.pinterest.com/pin/304907837243541263/",
                    "via_pinner": ""
                },
                "_type": "pin"
            },
            {
                "_id": "317151998732380071",
                "_index": "pinterest",
                "_score": 1.1964573,
                "_source": {
                    "board": "317152067447776865",
                    "comment_count": "0",
                    "created": "Mon, 18 Aug 2014 17:24:23 +0000",
                    "description": "CUSTOM EXTERIOR WOOD WINDOW AND DOOR SHUTTERS 48\" X 14\" WIDE - OR SPECIFY SIZE",
                    "domain": "ebay.com",
                    "id": "317151998732380071",
                    "image": "https://s-media-cache-ak0.pinimg.com/736x/75/af/08/75af084e42bdb0f9dc738c682dd2b6d4.jpg",
                    "image236": "https://s-media-cache-ak0.pinimg.com/236x/75/af/08/75af084e42bdb0f9dc738c682dd2b6d4.jpg",
                    "image60": "https://s-media-cache-ak0.pinimg.com/60x60/75/af/08/75af084e42bdb0f9dc738c682dd2b6d4.jpg",
                    "is_banned": "",
                    "is_repin": "",
                    "likes": "0",
                    "pin_join": "",
                    "pinner": "317152136167181292",
                    "place": "",
                    "price": "0",
                    "price_currency": "USD",
                    "repins": "1",
                    "source": "http://www.ebay.com/itm/CUSTOM-EXTERIOR-WOOD-WINDOW-AND-DOOR-SHUTTERS-48-X-14-WIDE-OR-SPECIFY-SIZE-/171416161068?roken=cUgayN",
                    "title": "Custom exterior wood window and door shutters 48\" x 14\" wide - or specify size",
                    "type": "pin",
                    "url": "https://www.pinterest.com/pin/317151998732380071/",
                    "via_pinner": ""
                },
                "_type": "pin"
            },
            {
                "_id": "344032859004226366",
                "_index": "pinterest",
                "_score": 1.0990341,
                "_source": {
                    "board": "344032927723569937",
                    "comment_count": "0",
                    "created": "Sat, 27 Oct 2012 04:14:12 +0000",
                    "description": "Summer Window Box, Petunia, Osteopermum, Window, Shutter, Lace Curtain",
                    "domain": "art.com",
                    "id": "344032859004226366",
                    "image": "https://s-media-cache-ak0.pinimg.com/736x/21/59/6b/21596bddca50797bb7cb1a97f22d6f38.jpg",
                    "image236": "https://s-media-cache-ak0.pinimg.com/236x/21/59/6b/21596bddca50797bb7cb1a97f22d6f38.jpg",
                    "image60": "https://s-media-cache-ak0.pinimg.com/60x60/21/59/6b/21596bddca50797bb7cb1a97f22d6f38.jpg",
                    "is_banned": "",
                    "is_repin": "",
                    "likes": "1",
                    "pin_join": "21596bddca50797bb7cb1a97f22d6f38",
                    "pinner": "344032996443033368",
                    "place": "",
                    "price": "0",
                    "price_currency": "USD",
                    "repins": "11",
                    "source": "http://www.art.com/products/p13815798-sa-i2759120/lynne-brotchie-summer-window-box-petunia-osteopermum-window-shutter-lace-curtain.htm#.UItffdbTAaU.pinterest",
                    "title": "Summer Window Box, Petunia, Osteopermum, Window, Shutter, Lace Curtain",
                    "type": "pin",
                    "url": "https://www.pinterest.com/pin/344032859004226366/",
                    "via_pinner": ""
                },
                "_type": "pin"
            },
            {
                "_id": "11540542768966089",
                "_index": "pinterest",
                "_score": 1.0500387,
                "_source": {
                    "board": "11540611484091043",
                    "comment_count": "0",
                    "created": "Wed, 30 Oct 2013 01:02:36 +0000",
                    "description": "Santa Rosa Window Curtain Tier Pairs and Valance",
                    "domain": "bedbathandbeyond.com",
                    "id": "11540542768966089",
                    "image": "https://s-media-cache-ak0.pinimg.com/736x/8b/e4/ba/8be4badef302718062a2635d22f2d7ac.jpg",
                    "image236": "https://s-media-cache-ak0.pinimg.com/236x/8b/e4/ba/8be4badef302718062a2635d22f2d7ac.jpg",
                    "image60": "https://s-media-cache-ak0.pinimg.com/60x60/8b/e4/ba/8be4badef302718062a2635d22f2d7ac.jpg",
                    "is_banned": "",
                    "is_repin": "",
                    "likes": "0",
                    "pin_join": "",
                    "pinner": "11540680203567306",
                    "place": "",
                    "price": "0",
                    "price_currency": "USD",
                    "repins": "0",
                    "source": "http://www.bedbathandbeyond.com/store/product/Santa-Rosa-Window-Curtain-Tier-Pairs-and-Valance/209917?categoryId=12156",
                    "title": "Santa Rosa Window Curtain Tier Pairs and Valance",
                    "type": "pin",
                    "url": "https://www.pinterest.com/pin/11540542768966089/",
                    "via_pinner": ""
                },
                "_type": "pin"
            },
            {
                "_id": "289004501060085734",
                "_index": "pinterest",
                "_score": 0.9135221,
                "_source": {
                    "board": "289004569776743890",
                    "comment_count": "0",
                    "created": "Thu, 27 Mar 2014 15:04:29 +0000",
                    "description": "art deco style window treatment idea, cornice, art deco valance top treatment",
                    "domain": "janebatemaninteriors.com",
                    "id": "289004501060085734",
                    "image": "https://s-media-cache-ak0.pinimg.com/736x/dd/f4/5e/ddf45ed568284304a130eef2d78aac5c.jpg",
                    "image236": "https://s-media-cache-ak0.pinimg.com/236x/dd/f4/5e/ddf45ed568284304a130eef2d78aac5c.jpg",
                    "image60": "https://s-media-cache-ak0.pinimg.com/60x60/dd/f4/5e/ddf45ed568284304a130eef2d78aac5c.jpg",
                    "is_banned": "",
                    "is_repin": "",
                    "likes": "2",
                    "pin_join": "ddf45ed568284304a130eef2d78aac5c",
                    "pinner": "289004638496114538",
                    "place": "",
                    "price": "0",
                    "price_currency": "USD",
                    "repins": "7",
                    "source": "http://janebatemaninteriors.com/window-treatment-of-the-month-april/",
                    "title": "Decorating Art Deco style ",
                    "type": "pin",
                    "url": "https://www.pinterest.com/pin/289004501060085734/",
                    "via_pinner": ""
                },
                "_type": "pin"
            },
            {
                "_id": "367043438353225003",
                "_index": "pinterest",
                "_score": 0.7780281,
                "_source": {
                    "board": "367043507069750087",
                    "comment_count": "0",
                    "created": "Fri, 28 Mar 2014 00:32:16 +0000",
                    "description": "Old+window+balconies+in+Spain | decorated closed window and postbox in spanish town",
                    "domain": "colourbox.com",
                    "id": "367043438353225003",
                    "image": "https://s-media-cache-ak0.pinimg.com/736x/58/30/cf/5830cf5dbb306ea49e1c1b660e581bd4.jpg",
                    "image236": "https://s-media-cache-ak0.pinimg.com/236x/58/30/cf/5830cf5dbb306ea49e1c1b660e581bd4.jpg",
                    "image60": "https://s-media-cache-ak0.pinimg.com/60x60/58/30/cf/5830cf5dbb306ea49e1c1b660e581bd4.jpg",
                    "is_banned": "",
                    "is_repin": "",
                    "likes": "0",
                    "pin_join": "",
                    "pinner": "367043575789126573",
                    "place": "",
                    "price": "0",
                    "price_currency": "USD",
                    "repins": "1",
                    "source": "http://www.colourbox.com/image/decorated-closed-window-and-postbox-in-spanish-town-image-3007513",
                    "title": "Romantic Windows",
                    "type": "pin",
                    "url": "https://www.pinterest.com/pin/367043438353225003/",
                    "via_pinner": ""
                },
                "_type": "pin"
            },
            {
                "_id": "280630620504931173",
                "_index": "pinterest",
                "_score": 0.7300016,
                "_source": {
                    "board": "280630689219481427",
                    "comment_count": "0",
                    "created": "Sat, 15 Mar 2014 23:17:26 +0000",
                    "description": "Royal Velvet\u00ae Ally Window Treatments - JCPenney {a valance I don't hate!}",
                    "domain": "jcpenney.com",
                    "id": "280630620504931173",
                    "image": "https://s-media-cache-ak0.pinimg.com/736x/b3/71/2e/b3712e4b5194dec51c3b490a58066a48.jpg",
                    "image236": "https://s-media-cache-ak0.pinimg.com/236x/b3/71/2e/b3712e4b5194dec51c3b490a58066a48.jpg",
                    "image60": "https://s-media-cache-ak0.pinimg.com/60x60/b3/71/2e/b3712e4b5194dec51c3b490a58066a48.jpg",
                    "is_banned": "",
                    "is_repin": "",
                    "likes": "0",
                    "pin_join": "",
                    "pinner": "280630757938954681",
                    "place": "",
                    "price": "0",
                    "price_currency": "USD",
                    "repins": "3",
                    "source": "http://www.jcpenney.com/window/sale/royal-velvet-ally-window-treatments/prod.jump?ppId=ens6002540009&catId=cat100260226&subcatId=dept20022800026&deptId=dept20000011&pageSize=96&topDim=Top+Construction&topDimvalue=rod+pocket&dimCombo=Top+Construction%7C&dimComboVal=rod+pocket%7C&currentDim=Top+Construction&currentDimVal=rod+pocket&colorizedImg=DP1212201317350076M.tif&urlState=/window/shop-/curtains-drapes/rod-pocket/_/N-1noxaaZ15s/cat.jump",
                    "title": "Home",
                    "type": "pin",
                    "url": "https://www.pinterest.com/pin/280630620504931173/",
                    "via_pinner": ""
                },
                "_type": "pin"
            },
            {
                "_id": "488218415827478037",
                "_index": "pinterest",
                "_score": 0.72584444,
                "_source": {
                    "board": "488218484543702469",
                    "comment_count": "0",
                    "created": "Wed, 14 May 2014 15:14:19 +0000",
                    "description": "close window go home - http://69hdwallpapers.com/close-window-go-home/",
                    "domain": "69hdwallpapers.com",
                    "id": "488218415827478037",
                    "image": "https://s-media-cache-ak0.pinimg.com/736x/25/7a/ff/257aff71300f1a2b1f63be180246b27c.jpg",
                    "image236": "https://s-media-cache-ak0.pinimg.com/236x/25/7a/ff/257aff71300f1a2b1f63be180246b27c.jpg",
                    "image60": "https://s-media-cache-ak0.pinimg.com/60x60/25/7a/ff/257aff71300f1a2b1f63be180246b27c.jpg",
                    "is_banned": "",
                    "is_repin": "",
                    "likes": "0",
                    "pin_join": "",
                    "pinner": "488218553263086683",
                    "place": "",
                    "price": "0",
                    "price_currency": "USD",
                    "repins": "0",
                    "source": "http://69hdwallpapers.com/close-window-go-home/",
                    "title": "Free HD Wallpapers",
                    "type": "pin",
                    "url": "https://www.pinterest.com/pin/488218415827478037/",
                    "via_pinner": ""
                },
                "_type": "pin"
            },
            {
                "_id": "559431584932120559",
                "_index": "pinterest",
                "_score": 0.70579666,
                "_source": {
                    "board": "559431653651396831",
                    "comment_count": "0",
                    "created": "Wed, 21 Nov 2012 22:46:28 +0000",
                    "description": "Turn-Only and miscellaneous window hinges for PVC elements",
                    "domain": "g-u.com",
                    "id": "559431584932120559",
                    "image": "https://s-media-cache-ak0.pinimg.com/736x/99/42/ad/9942ad43299f3f11c5edaeed4f5e2f78.jpg",
                    "image236": "https://s-media-cache-ak0.pinimg.com/236x/99/42/ad/9942ad43299f3f11c5edaeed4f5e2f78.jpg",
                    "image60": "https://s-media-cache-ak0.pinimg.com/60x60/99/42/ad/9942ad43299f3f11c5edaeed4f5e2f78.jpg",
                    "is_banned": "",
                    "is_repin": "",
                    "likes": "0",
                    "pin_join": "",
                    "pinner": "559431722370863233",
                    "place": "",
                    "price": "0",
                    "price_currency": "USD",
                    "repins": "0",
                    "source": "http://www.g-u.com/en/window-technology/accessories-for-buildersapos-hardware/turn-only-and-miscellaneous-window-hinges/pvc-elements.html",
                    "title": "architectural hardware",
                    "type": "pin",
                    "url": "https://www.pinterest.com/pin/559431584932120559/",
                    "via_pinner": ""
                },
                "_type": "pin"
            },
            {
                "_id": "339107046914512792",
                "_index": "pinterest",
                "_score": 0.6996761,
                "_source": {
                    "board": "339107115631221311",
                    "comment_count": "0",
                    "created": "Mon, 10 Feb 2014 02:14:26 +0000",
                    "description": "Window Tinting",
                    "domain": "popsautoelectric.com",
                    "id": "339107046914512792",
                    "image": "https://s-media-cache-ak0.pinimg.com/736x/3b/1d/a0/3b1da0595252beec2a20da24075b70f8.jpg",
                    "image236": "https://s-media-cache-ak0.pinimg.com/236x/3b/1d/a0/3b1da0595252beec2a20da24075b70f8.jpg",
                    "image60": "https://s-media-cache-ak0.pinimg.com/60x60/3b/1d/a0/3b1da0595252beec2a20da24075b70f8.jpg",
                    "is_banned": "",
                    "is_repin": "",
                    "likes": "0",
                    "pin_join": "",
                    "pinner": "339107184350606835",
                    "place": "",
                    "price": "0",
                    "price_currency": "USD",
                    "repins": "0",
                    "source": "http://www.popsautoelectric.com/window-tinting/",
                    "title": "Window Tinting By Pops Auto Electric Orlando, Florida",
                    "type": "pin",
                    "url": "https://www.pinterest.com/pin/339107046914512792/",
                    "via_pinner": ""
                },
                "_type": "pin"
            },
            {
                "_id": "76139049922216294",
                "_index": "pinterest",
                "_score": 0.67975223,
                "_source": {
                    "board": "76139118639202749",
                    "comment_count": "0",
                    "created": "Mon, 21 Jan 2013 17:32:17 +0000",
                    "description": "Living Room Window Treatment Design, Pictures, Remodel, Decor and Ideas",
                    "domain": "houzz.com",
                    "id": "76139049922216294",
                    "image": "https://s-media-cache-ak0.pinimg.com/736x/3a/b1/53/3ab15338508616ca6dd54a30a7a8b6e8.jpg",
                    "image236": "https://s-media-cache-ak0.pinimg.com/236x/3a/b1/53/3ab15338508616ca6dd54a30a7a8b6e8.jpg",
                    "image60": "https://s-media-cache-ak0.pinimg.com/60x60/3a/b1/53/3ab15338508616ca6dd54a30a7a8b6e8.jpg",
                    "is_banned": "",
                    "is_repin": "1",
                    "likes": "1",
                    "pin_join": "",
                    "pinner": "76139187358664601",
                    "place": "",
                    "price": "0",
                    "price_currency": "USD",
                    "repins": "6",
                    "source": "http://www.houzz.com/living-room-window-treatment",
                    "title": "For the Home",
                    "type": "pin",
                    "url": "https://www.pinterest.com/pin/76139049922216294/",
                    "via_pinner": "268738440172929511"
                },
                "_type": "pin"
            },
            {
                "_id": "108227197265708365",
                "_index": "pinterest",
                "_score": 0.6439887,
                "_source": {
                    "board": "108227265984234750",
                    "comment_count": "0",
                    "created": "Tue, 29 May 2012 15:48:38 +0000",
                    "description": "Grab attention with this shattered glass illusion clear vinyl clingBuy our green awareness shatter window ribbon cling for yourself or your next event to raise awareness for green ribbon causes.This 6\" diameter vinyl static cling attaches to glass from either side. The vinyl is clear, with white \"cracks\" and the colored text and ribbon. Use a few drops of water and smooth it onto glass.  Easy on, easy off.  Also works on glass in your entryway, a whiteboard at work, or other smooth surface. O...",
                    "domain": "bumperstickermagnet.com",
                    "id": "108227197265708365",
                    "image": "https://s-media-cache-ak0.pinimg.com/736x/05/53/ee/0553ee96237e20863ce173e841948404.jpg",
                    "image236": "https://s-media-cache-ak0.pinimg.com/236x/05/53/ee/0553ee96237e20863ce173e841948404.jpg",
                    "image60": "https://s-media-cache-ak0.pinimg.com/60x60/05/53/ee/0553ee96237e20863ce173e841948404.jpg",
                    "is_banned": "",
                    "is_repin": "",
                    "likes": "0",
                    "pin_join": "",
                    "pinner": "108227334703681429",
                    "place": "",
                    "price": "0",
                    "price_currency": "USD",
                    "repins": "2",
                    "source": "http://www.bumperstickermagnet.com/find-the-cure-shatter-static-window-cling-green.html",
                    "title": "My Causes",
                    "type": "pin",
                    "url": "https://www.pinterest.com/pin/108227197265708365/",
                    "via_pinner": ""
                },
                "_type": "pin"
            },
            {
                "_id": "288230444875397224",
                "_index": "pinterest",
                "_score": 0.64194494,
                "_source": {
                    "board": "288230513590835308",
                    "comment_count": "0",
                    "created": "Mon, 14 Jul 2014 04:58:08 +0000",
                    "description": "9 Charming Inexpensive Window Coverings",
                    "domain": "toppica.com",
                    "id": "288230444875397224",
                    "image": "https://s-media-cache-ak0.pinimg.com/736x/00/41/a3/0041a36fdd22567e8474f299d19b3760.jpg",
                    "image236": "https://s-media-cache-ak0.pinimg.com/236x/00/41/a3/0041a36fdd22567e8474f299d19b3760.jpg",
                    "image60": "https://s-media-cache-ak0.pinimg.com/60x60/00/41/a3/0041a36fdd22567e8474f299d19b3760.jpg",
                    "is_banned": "",
                    "is_repin": "",
                    "likes": "0",
                    "pin_join": "0041a36fdd22567e8474f299d19b3760",
                    "pinner": "288230582310171237",
                    "place": "",
                    "price": "0",
                    "price_currency": "USD",
                    "repins": "0",
                    "source": "http://toppica.com/9-charming-inexpensive-window-coverings/",
                    "title": "Window Treatments",
                    "type": "pin",
                    "url": "https://www.pinterest.com/pin/288230444875397224/",
                    "via_pinner": ""
                },
                "_type": "pin"
            },
            {
                "_id": "560838959815741745",
                "_index": "pinterest",
                "_score": 0.6119137,
                "_source": {
                    "board": "560839028534949371",
                    "comment_count": "0",
                    "created": "Tue, 25 Dec 2012 23:20:14 +0000",
                    "description": "Window Phone Concept  Is it a window, is it a phone? No. Actually, it\u2019s Window phone and this is the part where you are saying \u201cWhaaat? What are you talking about?\u201d. The phone is actually a concept with extraordinary features. Surely if this could be actually put into production, it would set a new standard for the term \u201ccool\u201d.    thanks to Amazing Facts for sharing!",
                    "domain": "facebook.com",
                    "id": "560838959815741745",
                    "image": "https://s-media-cache-ak0.pinimg.com/736x/9a/0b/f9/9a0bf9a90c40dc592920f401a084ee6c.jpg",
                    "image236": "https://s-media-cache-ak0.pinimg.com/236x/9a/0b/f9/9a0bf9a90c40dc592920f401a084ee6c.jpg",
                    "image60": "https://s-media-cache-ak0.pinimg.com/60x60/9a/0b/f9/9a0bf9a90c40dc592920f401a084ee6c.jpg",
                    "is_banned": "",
                    "is_repin": "",
                    "likes": "3",
                    "pin_join": "9a0bf9a90c40dc592920f401a084ee6c",
                    "pinner": "560839097254414768",
                    "place": "",
                    "price": "0",
                    "price_currency": "USD",
                    "repins": "5",
                    "source": "https://www.facebook.com/amazingfactsandphotos?ref=stream",
                    "title": "Neat Ideas \u0b90",
                    "type": "pin",
                    "url": "https://www.pinterest.com/pin/560838959815741745/",
                    "via_pinner": ""
                },
                "_type": "pin"
            },
            {
                "_id": "59532026295780983",
                "_index": "pinterest",
                "_score": 0.6103039,
                "_source": {
                    "board": "59532095013318275",
                    "comment_count": "0",
                    "created": "Wed, 21 Nov 2012 12:44:27 +0000",
                    "description": "Waldorf Window Stars ~ Mom's Crafty Space",
                    "domain": "momscraftyspace.com",
                    "id": "59532026295780983",
                    "image": "https://s-media-cache-ak0.pinimg.com/736x/18/9b/33/189b3357fa4be270b8bd8f2290d97eb4.jpg",
                    "image236": "https://s-media-cache-ak0.pinimg.com/236x/18/9b/33/189b3357fa4be270b8bd8f2290d97eb4.jpg",
                    "image60": "https://s-media-cache-ak0.pinimg.com/60x60/18/9b/33/189b3357fa4be270b8bd8f2290d97eb4.jpg",
                    "is_banned": "",
                    "is_repin": "",
                    "likes": "0",
                    "pin_join": "",
                    "pinner": "59532163732736114",
                    "place": "",
                    "price": "0",
                    "price_currency": "USD",
                    "repins": "2",
                    "source": "http://www.momscraftyspace.com/2011/03/waldorf-window-stars.html",
                    "title": "Waldorf Window Stars",
                    "type": "pin",
                    "url": "https://www.pinterest.com/pin/59532026295780983/",
                    "via_pinner": ""
                },
                "_type": "pin"
            },
            {
                "_id": "245657354645297569",
                "_index": "pinterest",
                "_score": 0.6098889,
                "_source": {
                    "board": "245657423363185762",
                    "comment_count": "0",
                    "created": "Thu, 30 Aug 2012 14:33:18 +0000",
                    "description": "Turquoise Chalkboard Window with Fabric Covered Corkboard. $70.00, via Etsy.",
                    "domain": "etsy.com",
                    "id": "245657354645297569",
                    "image": "https://s-media-cache-ak0.pinimg.com/736x/9d/99/e7/9d99e7eec1ce219f3ce0a8e339841de8.jpg",
                    "image236": "https://s-media-cache-ak0.pinimg.com/236x/9d/99/e7/9d99e7eec1ce219f3ce0a8e339841de8.jpg",
                    "image60": "https://s-media-cache-ak0.pinimg.com/60x60/9d/99/e7/9d99e7eec1ce219f3ce0a8e339841de8.jpg",
                    "is_banned": "",
                    "is_repin": "",
                    "likes": "0",
                    "pin_join": "9d99e7eec1ce219f3ce0a8e339841de8",
                    "pinner": "245657492082656035",
                    "place": "",
                    "price": "70",
                    "price_currency": "USD",
                    "repins": "3",
                    "source": "http://www.etsy.com/listing/104252619/turquoise-chalkboard-window-with-fabric?ref=sr_gallery_11&ga_search_query=chalkboard+window&ga_view_type=gallery&ga_ship_to=ZZ&ga_min=0&ga_max=0&ga_search_type=all",
                    "title": "Crafty",
                    "type": "pin",
                    "url": "https://www.pinterest.com/pin/245657354645297569/",
                    "via_pinner": ""
                },
                "_type": "pin"
            },
            {
                "_id": "188095721906486722",
                "_index": "pinterest",
                "_score": 0.60589224,
                "_source": {
                    "board": "188095790625855908",
                    "comment_count": "0",
                    "created": "Fri, 11 Nov 2011 05:38:21 +0000",
                    "description": "window",
                    "domain": "picasaweb.google.com",
                    "id": "188095721906486722",
                    "image": "https://s-media-cache-ak0.pinimg.com/736x/5f/92/aa/5f92aa6c93cb7f791ddccd52207b4500.jpg",
                    "image236": "https://s-media-cache-ak0.pinimg.com/236x/5f/92/aa/5f92aa6c93cb7f791ddccd52207b4500.jpg",
                    "image60": "https://s-media-cache-ak0.pinimg.com/60x60/5f/92/aa/5f92aa6c93cb7f791ddccd52207b4500.jpg",
                    "is_banned": "",
                    "is_repin": "1",
                    "likes": "0",
                    "pin_join": "5f92aa6c93cb7f791ddccd52207b4500",
                    "pinner": "188095859345326485",
                    "place": "",
                    "price": "0",
                    "price_currency": "USD",
                    "repins": "4",
                    "source": "http://picasaweb.google.com/lh/photo/X-CabJ6QZSP4QJjL-d6RKQ?feat=embedwebsite",
                    "title": "When one door closes, a window opens!",
                    "type": "pin",
                    "url": "https://www.pinterest.com/pin/188095721906486722/",
                    "via_pinner": ""
                },
                "_type": "pin"
            },
            {
                "_id": "301952349989595038",
                "_index": "pinterest",
                "_score": 0.59491163,
                "_source": {
                    "board": "301952418705452239",
                    "comment_count": "0",
                    "created": "Tue, 24 Jun 2014 18:05:07 +0000",
                    "description": "Exterior Decoration Design Plush Cozy Wooden House with a Unique Design that uses Roof House Such as Rustic and Double Window on the Roof House is also on a Beige Colored Walls House are Wonderful Ideas",
                    "domain": "azray.com",
                    "id": "301952349989595038",
                    "image": "https://s-media-cache-ak0.pinimg.com/736x/64/65/5c/64655c7f39ce1ca06b0ab263dff92844.jpg",
                    "image236": "https://s-media-cache-ak0.pinimg.com/236x/64/65/5c/64655c7f39ce1ca06b0ab263dff92844.jpg",
                    "image60": "https://s-media-cache-ak0.pinimg.com/60x60/64/65/5c/64655c7f39ce1ca06b0ab263dff92844.jpg",
                    "is_banned": "",
                    "is_repin": "",
                    "likes": "0",
                    "pin_join": "64655c7f39ce1ca06b0ab263dff92844",
                    "pinner": "301952487424814445",
                    "place": "",
                    "price": "0",
                    "price_currency": "USD",
                    "repins": "0",
                    "source": "http://azray.com/wonderful-wooden-house-design-ideas-in-2014/exterior-decoration-design-plush-cozy-wooden-house-with-a-unique-design-that-uses-roof-house-such-as-rustic-and-double-window-on-the-roof-house-is-also-on-a-beige-colored-walls-house-are-wonderful-ide/",
                    "title": "Home Architecture",
                    "type": "pin",
                    "url": "https://www.pinterest.com/pin/301952349989595038/",
                    "via_pinner": ""
                },
                "_type": "pin"
            },
            {
                "_id": "399835273137833355",
                "_index": "pinterest",
                "_score": 0.59430885,
                "_source": {
                    "board": "399835341856482463",
                    "comment_count": "0",
                    "created": "Thu, 02 May 2013 21:10:29 +0000",
                    "description": "Top Quality Replacement Windows and Vinyl Replacement Windows. Best replacement windows to fit your world, a wide selection of custom-made windows to fit your home. Visit the site for more details. http://castlewindows.com",
                    "domain": "youtube.com",
                    "id": "399835273137833355",
                    "image": "https://s-media-cache-ak0.pinimg.com/736x/91/bc/6c/91bc6ce5803666f2992abf4ddcfb5718.jpg",
                    "image236": "https://s-media-cache-ak0.pinimg.com/236x/91/bc/6c/91bc6ce5803666f2992abf4ddcfb5718.jpg",
                    "image60": "https://s-media-cache-ak0.pinimg.com/60x60/91/bc/6c/91bc6ce5803666f2992abf4ddcfb5718.jpg",
                    "is_banned": "",
                    "is_repin": "",
                    "likes": "0",
                    "pin_join": "",
                    "pinner": "399835410575927863",
                    "place": "",
                    "price": "0",
                    "price_currency": "USD",
                    "repins": "0",
                    "source": "http://www.youtube.com/watch?v=VGxWYFmXNrE&feature=share",
                    "title": "Top Quality Replacement Windows and Vinyl Replacement Window",
                    "type": "pin",
                    "url": "https://www.pinterest.com/pin/399835273137833355/",
                    "via_pinner": ""
                },
                "_type": "pin"
            },
            {
                "_id": "398639004486385602",
                "_index": "pinterest",
                "_score": 0.5857652,
                "_source": {
                    "board": "398639073205448211",
                    "comment_count": "0",
                    "created": "Tue, 29 Jan 2013 13:54:47 +0000",
                    "description": "God\u2019s Window - God\u2019s Window is a popular vantage point along the Drakensberg escarpment, at the southern extremity of the Nature Reserve.    Here, sheer cliffs plunge over 700 metres to the lowveld. From this escarpment\u2014a mostly unbroken rampart of cliffs\u2014opens a vista into the lowvelt expanse and escarpment forests, the Eden-like aesthetic appearance of which prompted the name.",
                    "domain": "whats-up.co.za",
                    "id": "398639004486385602",
                    "image": "https://s-media-cache-ak0.pinimg.com/736x/42/c7/15/42c7159a38d547b8d645b5916f144b8c.jpg",
                    "image236": "https://s-media-cache-ak0.pinimg.com/236x/42/c7/15/42c7159a38d547b8d645b5916f144b8c.jpg",
                    "image60": "https://s-media-cache-ak0.pinimg.com/60x60/42/c7/15/42c7159a38d547b8d645b5916f144b8c.jpg",
                    "is_banned": "",
                    "is_repin": "",
                    "likes": "0",
                    "pin_join": "42c7159a38d547b8d645b5916f144b8c",
                    "pinner": "398639141924896984",
                    "place": "",
                    "price": "0",
                    "price_currency": "USD",
                    "repins": "5",
                    "source": "http://www.whats-up.co.za/venue/gods-window/",
                    "title": "Place Of Interest",
                    "type": "pin",
                    "url": "https://www.pinterest.com/pin/398639004486385602/",
                    "via_pinner": ""
                },
                "_type": "pin"
            },
            {
                "_id": "344455071470513952",
                "_index": "pinterest",
                "_score": 0.5700542,
                "_source": {
                    "board": "344455140188674367",
                    "comment_count": "0",
                    "created": "Sat, 10 Aug 2013 04:56:06 +0000",
                    "description": "Metal Window Large Unisex Watch White  Metallic Casing in Elegant Shape  Plain Black Design on Watchface  Leather Wristband  Rhinestones on Watch Buckle  Watch Makes One Size Fits All   Rhinestones Watch Frame on the Dial   Silver Toned  Hardware  All Batteries Are Changed When Order Is Shipped   Comes Packaged In Felt-Pillowed GIFT BOX  Approximate Size:  3 L x 3 H x 2 W  Color:White  Model:  WT 187",
                    "domain": "fashionvogues.com",
                    "id": "344455071470513952",
                    "image": "https://s-media-cache-ak0.pinimg.com/736x/bd/c2/44/bdc2445ebce77d841b49a09724dd4894.jpg",
                    "image236": "https://s-media-cache-ak0.pinimg.com/236x/bd/c2/44/bdc2445ebce77d841b49a09724dd4894.jpg",
                    "image60": "https://s-media-cache-ak0.pinimg.com/60x60/bd/c2/44/bdc2445ebce77d841b49a09724dd4894.jpg",
                    "is_banned": "",
                    "is_repin": "",
                    "likes": "1",
                    "pin_join": "bdc2445ebce77d841b49a09724dd4894",
                    "pinner": "344455208908109053",
                    "place": "",
                    "price": "0",
                    "price_currency": "USD",
                    "repins": "0",
                    "source": "http://fashionvogues.com/3925-metal-window-large-unisex-watch-white.html",
                    "title": "http://fashionvogues.com/",
                    "type": "pin",
                    "url": "https://www.pinterest.com/pin/344455071470513952/",
                    "via_pinner": ""
                },
                "_type": "pin"
            },
            {
                "_id": "354447433145470719",
                "_index": "pinterest",
                "_score": 0.56263345,
                "_source": {
                    "board": "354447501861972817",
                    "comment_count": "0",
                    "created": "Thu, 06 Mar 2014 08:25:44 +0000",
                    "description": "Window Cleaning Merton",
                    "domain": "cleaningservicesmerton.co.uk",
                    "id": "354447433145470719",
                    "image": "https://s-media-cache-ak0.pinimg.com/736x/31/03/79/310379d1d4f787576e60c58495106f00.jpg",
                    "image236": "https://s-media-cache-ak0.pinimg.com/236x/31/03/79/310379d1d4f787576e60c58495106f00.jpg",
                    "image60": "https://s-media-cache-ak0.pinimg.com/60x60/31/03/79/310379d1d4f787576e60c58495106f00.jpg",
                    "is_banned": "",
                    "is_repin": "",
                    "likes": "0",
                    "pin_join": "310379d1d4f787576e60c58495106f00",
                    "pinner": "354447570581346776",
                    "place": "",
                    "price": "0",
                    "price_currency": "USD",
                    "repins": "0",
                    "source": "http://cleaningservicesmerton.co.uk/window-cleaning/",
                    "title": "Window Cleaning Merton",
                    "type": "pin",
                    "url": "https://www.pinterest.com/pin/354447433145470719/",
                    "via_pinner": ""
                },
                "_type": "pin"
            },
            {
                "_id": "506514289310627023",
                "_index": "pinterest",
                "_score": 0.56108516,
                "_source": {
                    "board": "506514358029780838",
                    "comment_count": "0",
                    "created": "Wed, 02 Jan 2013 06:56:11 +0000",
                    "description": "Cane Chair Near Window Design, Pictures, Remodel, Decor and Ideas - page 201",
                    "domain": "houzz.com",
                    "id": "506514289310627023",
                    "image": "https://s-media-cache-ak0.pinimg.com/736x/3b/d7/f5/3bd7f5debc6d73f63cd33679a1e017b0.jpg",
                    "image236": "https://s-media-cache-ak0.pinimg.com/236x/3b/d7/f5/3bd7f5debc6d73f63cd33679a1e017b0.jpg",
                    "image60": "https://s-media-cache-ak0.pinimg.com/60x60/3b/d7/f5/3bd7f5debc6d73f63cd33679a1e017b0.jpg",
                    "is_banned": "",
                    "is_repin": "",
                    "likes": "0",
                    "pin_join": "3bd7f5debc6d73f63cd33679a1e017b0",
                    "pinner": "506514426749255956",
                    "place": "",
                    "price": "0",
                    "price_currency": "USD",
                    "repins": "1",
                    "source": "http://www.houzz.com/cane-chair-near-window/p/1600",
                    "title": "ideas for the home",
                    "type": "pin",
                    "url": "https://www.pinterest.com/pin/506514289310627023/",
                    "via_pinner": ""
                },
                "_type": "pin"
            },
            {
                "_id": "553028029212102698",
                "_index": "pinterest",
                "_score": 0.5546475,
                "_source": {
                    "board": "553028097931238077",
                    "comment_count": "0",
                    "created": "Tue, 01 Jan 2013 12:58:56 +0000",
                    "description": "Add four legs and a back to a window attached to its casing (or attach four legs and a window to a dresser drawer.",
                    "domain": "indulgy.com",
                    "id": "553028029212102698",
                    "image": "https://s-media-cache-ak0.pinimg.com/736x/4f/ab/49/4fab4949e33d2f49685f0d8ec97c1d5c.jpg",
                    "image236": "https://s-media-cache-ak0.pinimg.com/236x/4f/ab/49/4fab4949e33d2f49685f0d8ec97c1d5c.jpg",
                    "image60": "https://s-media-cache-ak0.pinimg.com/60x60/4f/ab/49/4fab4949e33d2f49685f0d8ec97c1d5c.jpg",
                    "is_banned": "",
                    "is_repin": "1",
                    "likes": "4",
                    "pin_join": "4fab4949e33d2f49685f0d8ec97c1d5c",
                    "pinner": "553028166650696393",
                    "place": "",
                    "price": "0",
                    "price_currency": "USD",
                    "repins": "5",
                    "source": "http://indulgy.com/post/2Nv7dZ9OD1/reuse-old-windows-as-coffee-tables#/lucinda/Upcycling%20Repurposing%20Recycling/from/59028741536",
                    "title": "Create Furniture",
                    "type": "pin",
                    "url": "https://www.pinterest.com/pin/553028029212102698/",
                    "via_pinner": ""
                },
                "_type": "pin"
            },
            {
                "_id": "106256872431116676",
                "_index": "pinterest",
                "_score": 0.5505661,
                "_source": {
                    "board": "106256941147334074",
                    "comment_count": "0",
                    "created": "Wed, 15 May 2013 05:27:51 +0000",
                    "description": "Window Planter hang the window and the planter on the front porch. ~ on our deck to draw attention away from the neighbors house",
                    "domain": "images.search.yahoo.com",
                    "id": "106256872431116676",
                    "image": "https://s-media-cache-ak0.pinimg.com/736x/45/5f/a2/455fa24dcdf35a065e2e2182aad31ca4.jpg",
                    "image236": "https://s-media-cache-ak0.pinimg.com/236x/45/5f/a2/455fa24dcdf35a065e2e2182aad31ca4.jpg",
                    "image60": "https://s-media-cache-ak0.pinimg.com/60x60/45/5f/a2/455fa24dcdf35a065e2e2182aad31ca4.jpg",
                    "is_banned": "",
                    "is_repin": "1",
                    "likes": "0",
                    "pin_join": "455fa24dcdf35a065e2e2182aad31ca4",
                    "pinner": "106257009866705228",
                    "place": "",
                    "price": "0",
                    "price_currency": "USD",
                    "repins": "5",
                    "source": "http://images.search.yahoo.com/images/view;_ylt=A0PDoX45dHJPwy4A8heJzbkF;_ylu=X3oDMTBlMTQ4cGxyBHNlYwNzcgRzbGsDaW1n?back=http%3A%2F%2Fimages.search.yahoo.com%2Fsearch%2Fimages%3Fp%3Dprimitive%2Boutdoor%2Bplanter%26n%3D30%26ei%3Dutf-8%26y%3DSearch%26fr%3Dyfp-t-701-21%26tab%3Dorganic%26ri%3D334&w=570&h=427&imgurl=img2.etsystatic.com%2Fil_570xN.174376858.jpg&rurl=http%3A%2F%2Fwww.etsy.com%2Flisting%2F56297090%2Fantique-window-with-flower-box&size=78.2+KB&name=antique+window+with+flower+box+by+Putzter+on+Etsy&p=primitive+outdoor+planter&oid=d2e05a5f878feae3b4f92c11da717f5f&fr2=&fr=yfp-t-701-21&tt=antique%2Bwindow%2Bwith%2Bflower%2Bbox%2Bby%2BPutzter%2Bon%2BEtsy&b=331&ni=30&no=334&tab=organic&ts=&sigr=123j0degu&sigb=142nc20go&sigi=11anmij7t&.crumb=ZohnkyvtBGp",
                    "title": "outside",
                    "type": "pin",
                    "url": "https://www.pinterest.com/pin/106256872431116676/",
                    "via_pinner": "17522023458672291"
                },
                "_type": "pin"
            },
            {
                "_id": "473018767082728455",
                "_index": "pinterest",
                "_score": 0.5458069,
                "_source": {
                    "board": "473018835801247660",
                    "comment_count": "0",
                    "created": "Sat, 20 Apr 2013 08:32:04 +0000",
                    "description": "Summer's Edge Patchwork Valance 16x72\" by Victorian Heart Co., Inc.. $12.95. Chambray blues and country reds take on a nautical feel in a classic patchwork pattern.. 100% cotton. Patch Valance 16x72\". Coordinating items are appliqued.. Available in quilts, bedding, window treatments, and pillows.. Our Summer's Edge pattern will transform your bedroom into a light and airy beach cottage escape!  Chambray blues and country reds take on a nautical feel in a classic ...",
                    "domain": "cometseven.com",
                    "id": "473018767082728455",
                    "image": "https://s-media-cache-ak0.pinimg.com/736x/08/79/b0/0879b052189700ac133fe835a1d37024.jpg",
                    "image236": "https://s-media-cache-ak0.pinimg.com/236x/08/79/b0/0879b052189700ac133fe835a1d37024.jpg",
                    "image60": "https://s-media-cache-ak0.pinimg.com/60x60/08/79/b0/0879b052189700ac133fe835a1d37024.jpg",
                    "is_banned": "",
                    "is_repin": "",
                    "likes": "1",
                    "pin_join": "",
                    "pinner": "473018904520696129",
                    "place": "",
                    "price": "0",
                    "price_currency": "USD",
                    "repins": "7",
                    "source": "http://cometseven.com/acusa/dpwwd/Bw0w0d3aEw1oDbZkWkCe.html",
                    "title": "Home & Kitchen",
                    "type": "pin",
                    "url": "https://www.pinterest.com/pin/473018767082728455/",
                    "via_pinner": ""
                },
                "_type": "pin"
            },
            {
                "_id": "197384396143173616",
                "_index": "pinterest",
                "_score": 0.5433965,
                "_source": {
                    "board": "197384464857335793",
                    "comment_count": "0",
                    "created": "Tue, 29 Apr 2014 16:50:12 +0000",
                    "description": "Mirror Cleaning:1 C. alcohol, 1 C. water, 1 t. vinegar. BEST mirror and window cleaner EVER! Not a streak one, even when the sun shines in the windows.",
                    "domain": "hometalk.com",
                    "id": "197384396143173616",
                    "image": "https://s-media-cache-ak0.pinimg.com/736x/65/21/7d/65217df78d27d991c0291996430cae04.jpg",
                    "image236": "https://s-media-cache-ak0.pinimg.com/236x/65/21/7d/65217df78d27d991c0291996430cae04.jpg",
                    "image60": "https://s-media-cache-ak0.pinimg.com/60x60/65/21/7d/65217df78d27d991c0291996430cae04.jpg",
                    "is_banned": "",
                    "is_repin": "",
                    "likes": "2",
                    "pin_join": "65217df78d27d991c0291996430cae04",
                    "pinner": "197384533576779585",
                    "place": "",
                    "price": "0",
                    "price_currency": "USD",
                    "repins": "13",
                    "source": "http://www.hometalk.com/3507686/mirror-cleaning-for-a-better-selfie?tk=qsp3gz&se=wkly",
                    "title": "Mirror Cleaning for a Better Selfie",
                    "type": "pin",
                    "url": "https://www.pinterest.com/pin/197384396143173616/",
                    "via_pinner": ""
                },
                "_type": "pin"
            },
            {
                "_id": "345932815100489587",
                "_index": "pinterest",
                "_score": 0.5406821,
                "_source": {
                    "board": "345932883816477743",
                    "comment_count": "0",
                    "created": "Sat, 17 May 2014 01:01:29 +0000",
                    "description": "Picture of",
                    "domain": "instructables.com",
                    "id": "345932815100489587",
                    "image": "https://s-media-cache-ak0.pinimg.com/736x/87/20/e2/8720e260c67e78fb958f8e981218e264.jpg",
                    "image236": "https://s-media-cache-ak0.pinimg.com/236x/87/20/e2/8720e260c67e78fb958f8e981218e264.jpg",
                    "image60": "https://s-media-cache-ak0.pinimg.com/60x60/87/20/e2/8720e260c67e78fb958f8e981218e264.jpg",
                    "is_banned": "",
                    "is_repin": "",
                    "likes": "0",
                    "pin_join": "",
                    "pinner": "345932952535852414",
                    "place": "",
                    "price": "0",
                    "price_currency": "USD",
                    "repins": "0",
                    "source": "http://www.instructables.com/id/Honda-Odyssey-Rear-Window-Motor-Repair/?ALLSTEPS",
                    "title": "Honda Odyssey Rear Window Motor Repair",
                    "type": "pin",
                    "url": "https://www.pinterest.com/pin/345932815100489587/",
                    "via_pinner": ""
                },
                "_type": "pin"
            },
            {
                "_id": "176484879122262355",
                "_index": "pinterest",
                "_score": 0.53761595,
                "_source": {
                    "board": "176484947836581143",
                    "comment_count": "0",
                    "created": "Tue, 18 Mar 2014 22:50:36 +0000",
                    "description": "Staircase window seat",
                    "domain": "meccinteriors.wordpress.com",
                    "id": "176484879122262355",
                    "image": "https://s-media-cache-ak0.pinimg.com/736x/1f/98/8e/1f988e09e92d392d58f4ee5e6f3a9110.jpg",
                    "image236": "https://s-media-cache-ak0.pinimg.com/236x/1f/98/8e/1f988e09e92d392d58f4ee5e6f3a9110.jpg",
                    "image60": "https://s-media-cache-ak0.pinimg.com/60x60/1f/98/8e/1f988e09e92d392d58f4ee5e6f3a9110.jpg",
                    "is_banned": "",
                    "is_repin": "",
                    "likes": "0",
                    "pin_join": "",
                    "pinner": "176485016556016536",
                    "place": "",
                    "price": "0",
                    "price_currency": "USD",
                    "repins": "1",
                    "source": "https://meccinteriors.wordpress.com/2015/03/30/5-reasons-to-consider-installing-a-window-seat/",
                    "title": "For the Home",
                    "type": "pin",
                    "url": "https://www.pinterest.com/pin/176484879122262355/",
                    "via_pinner": ""
                },
                "_type": "pin"
            },
            {
                "_id": "530228556099753713",
                "_index": "pinterest",
                "_score": 0.5347905,
                "_source": {
                    "board": "530228624817690322",
                    "comment_count": "0",
                    "created": "Tue, 17 Sep 2013 17:14:01 +0000",
                    "description": "Love This...You haven't been told nothing until it comes from Divine Creation [God]..even when 'man' can design the smoke mankind cannot control the Power of Wind even if it blows through an open window, an unexpected member arrives home and opens the door, the furnace/air conditioner blower starts to blow, or you are made my a Higher Divine Power to suddenly cough before you can turn away...The Divine Power and Divine Mysteries goes far, far beyond any human being...Love This in Divine Creation Panentheism ....",
                    "domain": "bijouxnoir.tumblr.com",
                    "id": "530228556099753713",
                    "image": "https://s-media-cache-ak0.pinimg.com/736x/8f/66/a6/8f66a66dbf5cb65f2e9799955f303650.jpg",
                    "image236": "https://s-media-cache-ak0.pinimg.com/236x/8f/66/a6/8f66a66dbf5cb65f2e9799955f303650.jpg",
                    "image60": "https://s-media-cache-ak0.pinimg.com/60x60/8f/66/a6/8f66a66dbf5cb65f2e9799955f303650.jpg",
                    "is_banned": "",
                    "is_repin": "1",
                    "likes": "3",
                    "pin_join": "8f66a66dbf5cb65f2e9799955f303650",
                    "pinner": "530228693537134727",
                    "place": "",
                    "price": "0",
                    "price_currency": "USD",
                    "repins": "3",
                    "source": "http://bijouxnoir.tumblr.com/page/650",
                    "title": "Divine Sacred Fire",
                    "type": "pin",
                    "url": "https://www.pinterest.com/pin/530228556099753713/",
                    "via_pinner": "147493093954814233"
                },
                "_type": "pin"
            },
            {
                "_id": "227009637441247112",
                "_index": "pinterest",
                "_score": 0.5337133,
                "_source": {
                    "board": "227009706156119074",
                    "comment_count": "0",
                    "created": "Sat, 25 Jan 2014 07:34:54 +0000",
                    "description": "Swag Window Treatments | Window Treatments at local Real Estate office",
                    "domain": "home.earthlink.net",
                    "id": "227009637441247112",
                    "image": "https://s-media-cache-ak0.pinimg.com/736x/5e/ca/38/5eca388cd6d807c12b0cd377b04ba2d4.jpg",
                    "image236": "https://s-media-cache-ak0.pinimg.com/236x/5e/ca/38/5eca388cd6d807c12b0cd377b04ba2d4.jpg",
                    "image60": "https://s-media-cache-ak0.pinimg.com/60x60/5e/ca/38/5eca388cd6d807c12b0cd377b04ba2d4.jpg",
                    "is_banned": "",
                    "is_repin": "",
                    "likes": "0",
                    "pin_join": "",
                    "pinner": "227009774875576962",
                    "place": "",
                    "price": "0",
                    "price_currency": "USD",
                    "repins": "2",
                    "source": "http://home.earthlink.net/~suggsdraperies/id13.html",
                    "title": "For the Home",
                    "type": "pin",
                    "url": "https://www.pinterest.com/pin/227009637441247112/",
                    "via_pinner": ""
                },
                "_type": "pin"
            },
            {
                "_id": "223913412693170423",
                "_index": "pinterest",
                "_score": 0.5293016,
                "_source": {
                    "board": "223913481412302256",
                    "comment_count": "0",
                    "created": "Tue, 07 Feb 2012 22:30:44 +0000",
                    "description": "Great idea for front door windows, bathroom windows, or anywhere else privacy is desired!",
                    "domain": "amazon.com",
                    "id": "223913412693170423",
                    "image": "https://s-media-cache-ak0.pinimg.com/736x/d8/99/e4/d899e41ed610ce11301bc420be68f4e0.jpg",
                    "image236": "https://s-media-cache-ak0.pinimg.com/236x/d8/99/e4/d899e41ed610ce11301bc420be68f4e0.jpg",
                    "image60": "https://s-media-cache-ak0.pinimg.com/60x60/d8/99/e4/d899e41ed610ce11301bc420be68f4e0.jpg",
                    "is_banned": "",
                    "is_repin": "",
                    "likes": "9",
                    "pin_join": "d899e41ed610ce11301bc420be68f4e0",
                    "pinner": "223913550131759606",
                    "place": "",
                    "price": "0",
                    "price_currency": "USD",
                    "repins": "42",
                    "source": "http://www.amazon.com/Etched-Lace-Window-Film-24-by-36-Inch/dp/B001MYLELC/ref=sr_1_31?s=home-garden&ie=UTF8&qid=1328653751&sr=1-31",
                    "title": "Living and Dining Space",
                    "type": "pin",
                    "url": "https://www.pinterest.com/pin/223913412693170423/",
                    "via_pinner": ""
                },
                "_type": "pin"
            },
            {
                "_id": "105764291223001788",
                "_index": "pinterest",
                "_score": 0.5267401,
                "_source": {
                    "board": "105764359938075009",
                    "comment_count": "0",
                    "created": "Tue, 26 Nov 2013 21:41:03 +0000",
                    "description": "Country Rustic Window Flower Box & Shutter idea for barn",
                    "domain": "r.ebay.com",
                    "id": "105764291223001788",
                    "image": "https://s-media-cache-ak0.pinimg.com/736x/25/19/35/251935772b8d80d511e16dcb3040b5ec.jpg",
                    "image236": "https://s-media-cache-ak0.pinimg.com/236x/25/19/35/251935772b8d80d511e16dcb3040b5ec.jpg",
                    "image60": "https://s-media-cache-ak0.pinimg.com/60x60/25/19/35/251935772b8d80d511e16dcb3040b5ec.jpg",
                    "is_banned": "",
                    "is_repin": "",
                    "likes": "0",
                    "pin_join": "",
                    "pinner": "105764428657459781",
                    "place": "",
                    "price": "0",
                    "price_currency": "USD",
                    "repins": "5",
                    "source": "http://r.ebay.com/2Tnec6",
                    "title": "Country Rustic Window Flower Box Shutter Wall Decal 37\" x 26\" NEW",
                    "type": "pin",
                    "url": "https://www.pinterest.com/pin/105764291223001788/",
                    "via_pinner": ""
                },
                "_type": "pin"
            },
            {
                "_id": "386887424208876488",
                "_index": "pinterest",
                "_score": 0.52547246,
                "_source": {
                    "board": "386887492927784843",
                    "comment_count": "0",
                    "created": "Wed, 06 Mar 2013 16:32:02 +0000",
                    "description": "window and curtain",
                    "domain": "windowdesignsbydiane.com",
                    "id": "386887424208876488",
                    "image": "https://s-media-cache-ak0.pinimg.com/736x/af/1c/9f/af1c9f26e7b227c89dafb28403d5a4a4.jpg",
                    "image236": "https://s-media-cache-ak0.pinimg.com/236x/af/1c/9f/af1c9f26e7b227c89dafb28403d5a4a4.jpg",
                    "image60": "https://s-media-cache-ak0.pinimg.com/60x60/af/1c/9f/af1c9f26e7b227c89dafb28403d5a4a4.jpg",
                    "is_banned": "",
                    "is_repin": "",
                    "likes": "1",
                    "pin_join": "",
                    "pinner": "386887561647235829",
                    "place": "",
                    "price": "0",
                    "price_currency": "USD",
                    "repins": "2",
                    "source": "http://www.windowdesignsbydiane.com/services.htm",
                    "title": "Window Designs",
                    "type": "pin",
                    "url": "https://www.pinterest.com/pin/386887424208876488/",
                    "via_pinner": ""
                },
                "_type": "pin"
            },
            {
                "_id": "392868767464568345",
                "_index": "pinterest",
                "_score": 0.5211944,
                "_source": {
                    "board": "392868836182914623",
                    "comment_count": "0",
                    "created": "Thu, 04 Jul 2013 12:28:41 +0000",
                    "description": "cottage window",
                    "domain": "google.fr",
                    "id": "392868767464568345",
                    "image": "https://s-media-cache-ak0.pinimg.com/736x/0f/ee/1a/0fee1ad8d9fb836d602fae04b4cb8070.jpg",
                    "image236": "https://s-media-cache-ak0.pinimg.com/236x/0f/ee/1a/0fee1ad8d9fb836d602fae04b4cb8070.jpg",
                    "image60": "https://s-media-cache-ak0.pinimg.com/60x60/0f/ee/1a/0fee1ad8d9fb836d602fae04b4cb8070.jpg",
                    "is_banned": "",
                    "is_repin": "",
                    "likes": "0",
                    "pin_join": "0fee1ad8d9fb836d602fae04b4cb8070",
                    "pinner": "392868904902332878",
                    "place": "",
                    "price": "0",
                    "price_currency": "USD",
                    "repins": "1",
                    "source": "https://www.google.fr/search?q=the+colour+chestnut&source=lnms&tbm=isch&sa=X&ei=TGfVUZTdKoWf0QWMvoGICw&ved=0CAcQ_AUoAQ&biw=1301&bih=650#tbm=isch&sa=1&q=cottage+window&oq=cottage+window&gs_l=img.3..0i19l10.101967.106369.8.106803.24.18.0.0.0.0.332.1777.3j5j1j2.11.0....0...1c.1.19.img.3jUXW3Xjl5E&bav=on.2,or.r_cp.r_qf.&fp=21ac31242fc0b721&biw=1301&bih=650",
                    "title": "Windows",
                    "type": "pin",
                    "url": "https://www.pinterest.com/pin/392868767464568345/",
                    "via_pinner": ""
                },
                "_type": "pin"
            },
            {
                "_id": "292311832038025300",
                "_index": "pinterest",
                "_score": 0.5198775,
                "_source": {
                    "board": "292311900753163591",
                    "comment_count": "0",
                    "created": "Wed, 30 Jul 2014 11:54:28 +0000",
                    "description": "looking out the window",
                    "domain": "google.nl",
                    "id": "292311832038025300",
                    "image": "https://s-media-cache-ak0.pinimg.com/736x/24/0c/21/240c21f6a9ce8f4d6b8e08890425c060.jpg",
                    "image236": "https://s-media-cache-ak0.pinimg.com/236x/24/0c/21/240c21f6a9ce8f4d6b8e08890425c060.jpg",
                    "image60": "https://s-media-cache-ak0.pinimg.com/60x60/24/0c/21/240c21f6a9ce8f4d6b8e08890425c060.jpg",
                    "is_banned": "",
                    "is_repin": "",
                    "likes": "0",
                    "pin_join": "240c21f6a9ce8f4d6b8e08890425c060",
                    "pinner": "292311969472448350",
                    "place": "",
                    "price": "0",
                    "price_currency": "USD",
                    "repins": "0",
                    "source": "https://www.google.nl/search?q=window&rlz=1C1CHFX_nlNL573NL573&source=lnms&tbm=isch&sa=X&ei=BtzYU6S2HIe1PJS7gKAI&ved=0CAgQ_AUoAQ&biw=1164&bih=584#q=looking+out+the+window&tbm=isch&facrc=_&imgdii=hKm1weLvZQm3jM:;2uqMGN31GlaQUM;hKm1weLvZQm3jM:&imgrc=hKm1weLvZQm3jM%253A;CrMs03NSlejB2M;http%253A%252F%252Fstatic.guim.co.uk%252Fsys-images%252FAdmin%252FBkFill%252FDefault_image_group%252F2013%252F8%252F13%252F1376409383616%252FLonely-girl-looking-out-o-010.jpg;http%253A%252F%252Fwww.theguardian.com%252Fbooks%252F2013%252Faug%252F18%252Fnever-list-koethi-zan-thriller;460;276",
                    "title": "window to the world",
                    "type": "pin",
                    "url": "https://www.pinterest.com/pin/292311832038025300/",
                    "via_pinner": ""
                },
                "_type": "pin"
            },
            {
                "_id": "562175965955600646",
                "_index": "pinterest",
                "_score": 0.51863587,
                "_source": {
                    "board": "562176034674351630",
                    "comment_count": "0",
                    "created": "Sun, 07 Apr 2013 15:26:46 +0000",
                    "description": "@Overstock.com - The die cut window frame is laminated onto a 1/8 inch thick mirror to give it its outstanding look.  This mirror can go in any room in the house, instantly giving it a bigger and brighter feel.http://www.overstock.com/Home-Garden/Toile-Planter-Mirror/6319421/product.html?CID=214117 $99.99",
                    "domain": "overstock.com",
                    "id": "562175965955600646",
                    "image": "https://s-media-cache-ak0.pinimg.com/736x/2d/51/3d/2d513ddc63a99693f3a2d07dc0728b90.jpg",
                    "image236": "https://s-media-cache-ak0.pinimg.com/236x/2d/51/3d/2d513ddc63a99693f3a2d07dc0728b90.jpg",
                    "image60": "https://s-media-cache-ak0.pinimg.com/60x60/2d/51/3d/2d513ddc63a99693f3a2d07dc0728b90.jpg",
                    "is_banned": "",
                    "is_repin": "1",
                    "likes": "0",
                    "pin_join": "2d513ddc63a99693f3a2d07dc0728b90",
                    "pinner": "562176103393788047",
                    "place": "",
                    "price": "99.99",
                    "price_currency": "USD",
                    "repins": "1",
                    "source": "http://www.overstock.com/Home-Garden/Toile-Planter-Mirror/6319421/product.html?CID=214117",
                    "title": "Toile Planter Mirror",
                    "type": "pin",
                    "url": "https://www.pinterest.com/pin/562175965955600646/",
                    "via_pinner": ""
                },
                "_type": "pin"
            },
            {
                "_id": "180566266285234982",
                "_index": "pinterest",
                "_score": 0.5165255,
                "_source": {
                    "board": "180566334998863570",
                    "comment_count": "0",
                    "created": "Tue, 08 Jul 2014 19:15:51 +0000",
                    "description": "These Custom Printed Window Signs in the shape of a Breast Cancer Awareness Ribbon are great to promote upcoming breast cancer fundraisers and events. They are priced low enough to pass out in mass to ensure a successful event. These measure 5.875\" W x 9.75\" H.",
                    "domain": "perfectimprints.com",
                    "id": "180566266285234982",
                    "image": "https://s-media-cache-ak0.pinimg.com/736x/34/b3/41/34b3418a6863703ae09c361cf53032b8.jpg",
                    "image236": "https://s-media-cache-ak0.pinimg.com/236x/34/b3/41/34b3418a6863703ae09c361cf53032b8.jpg",
                    "image60": "https://s-media-cache-ak0.pinimg.com/60x60/34/b3/41/34b3418a6863703ae09c361cf53032b8.jpg",
                    "is_banned": "",
                    "is_repin": "",
                    "likes": "0",
                    "pin_join": "34b3418a6863703ae09c361cf53032b8",
                    "pinner": "180566403718318832",
                    "place": "",
                    "price": "0",
                    "price_currency": "USD",
                    "repins": "0",
                    "source": "http://perfectimprints.com/breast-cancer-awareness-ribbon-stock-window-sign.html",
                    "title": "Breast Cancer Awareness",
                    "type": "pin",
                    "url": "https://www.pinterest.com/pin/180566266285234982/",
                    "via_pinner": ""
                },
                "_type": "pin"
            },
            {
                "_id": "246783254550840609",
                "_index": "pinterest",
                "_score": 0.51008457,
                "_source": {
                    "board": "246783323270106061",
                    "comment_count": "0",
                    "created": "Thu, 26 Jan 2012 05:15:39 +0000",
                    "description": "These started out as plain white tab curtains from Ikea. I cut off the tabs  And with a couple yards of black fabric.  I sewed 12\" black stripes on to them. DIY by the diary of daves wife chick",
                    "domain": "thediaryofdaveswife.com",
                    "id": "246783254550840609",
                    "image": "https://s-media-cache-ak0.pinimg.com/736x/f5/4b/3e/f54b3ecbbeeadd1381c550c60399f29c.jpg",
                    "image236": "https://s-media-cache-ak0.pinimg.com/236x/f5/4b/3e/f54b3ecbbeeadd1381c550c60399f29c.jpg",
                    "image60": "https://s-media-cache-ak0.pinimg.com/60x60/f5/4b/3e/f54b3ecbbeeadd1381c550c60399f29c.jpg",
                    "is_banned": "",
                    "is_repin": "1",
                    "likes": "4",
                    "pin_join": "f54b3ecbbeeadd1381c550c60399f29c",
                    "pinner": "246783391989499707",
                    "place": "",
                    "price": "0",
                    "price_currency": "USD",
                    "repins": "13",
                    "source": "http://www.thediaryofdaveswife.com/2011/04/extreme-make-over-daveswife-edition.html",
                    "title": "Window Treatments",
                    "type": "pin",
                    "url": "https://www.pinterest.com/pin/246783254550840609/",
                    "via_pinner": ""
                },
                "_type": "pin"
            },
            {
                "_id": "201184308325138944",
                "_index": "pinterest",
                "_score": 0.5068511,
                "_source": {
                    "board": "201184377042918835",
                    "comment_count": "0",
                    "created": "Mon, 17 Sep 2012 21:39:22 +0000",
                    "description": "Own Work (Regus & Co) - Window deco at HiFi Klubben in Kolding, Denmark ... See more by following the picture :)",
                    "domain": "helena-wp.tumblr.com",
                    "id": "201184308325138944",
                    "image": "https://s-media-cache-ak0.pinimg.com/736x/a7/4c/c1/a74cc1d5e396fc08fa9322d008c5c4f4.jpg",
                    "image236": "https://s-media-cache-ak0.pinimg.com/236x/a7/4c/c1/a74cc1d5e396fc08fa9322d008c5c4f4.jpg",
                    "image60": "https://s-media-cache-ak0.pinimg.com/60x60/a7/4c/c1/a74cc1d5e396fc08fa9322d008c5c4f4.jpg",
                    "is_banned": "",
                    "is_repin": "",
                    "likes": "0",
                    "pin_join": "a74cc1d5e396fc08fa9322d008c5c4f4",
                    "pinner": "201184445762374427",
                    "place": "",
                    "price": "0",
                    "price_currency": "USD",
                    "repins": "0",
                    "source": "http://helena-wp.tumblr.com/post/31751148047/window-deco-together-with-susanne-ragus-ragus",
                    "title": "Visual Merchandising",
                    "type": "pin",
                    "url": "https://www.pinterest.com/pin/201184308325138944/",
                    "via_pinner": ""
                },
                "_type": "pin"
            },
            {
                "_id": "344384702728389115",
                "_index": "pinterest",
                "_score": 0.50624496,
                "_source": {
                    "board": "344384771444560772",
                    "comment_count": "0",
                    "created": "Thu, 08 May 2014 09:36:53 +0000",
                    "description": "Clementine and Olive Life Style Blog: Easy Window Cornice DIY // bathroom peek",
                    "domain": "clementineandolive.blogspot.com",
                    "id": "344384702728389115",
                    "image": "https://s-media-cache-ak0.pinimg.com/736x/98/e9/b7/98e9b7a4ec0307c9c922ab41c1541434.jpg",
                    "image236": "https://s-media-cache-ak0.pinimg.com/236x/98/e9/b7/98e9b7a4ec0307c9c922ab41c1541434.jpg",
                    "image60": "https://s-media-cache-ak0.pinimg.com/60x60/98/e9/b7/98e9b7a4ec0307c9c922ab41c1541434.jpg",
                    "is_banned": "",
                    "is_repin": "",
                    "likes": "0",
                    "pin_join": "98e9b7a4ec0307c9c922ab41c1541434",
                    "pinner": "344384840163942822",
                    "place": "",
                    "price": "0",
                    "price_currency": "USD",
                    "repins": "0",
                    "source": "http://clementineandolive.blogspot.com/2013/05/easy-window-cornice-diy.html?m=1",
                    "title": "Sebastian",
                    "type": "pin",
                    "url": "https://www.pinterest.com/pin/344384702728389115/",
                    "via_pinner": ""
                },
                "_type": "pin"
            },
            {
                "_id": "341710690447547116",
                "_index": "pinterest",
                "_score": 0.5013217,
                "_source": {
                    "board": "341710759165946631",
                    "comment_count": "0",
                    "created": "Mon, 22 Jul 2013 05:26:56 +0000",
                    "description": "Window Curtains Hardware - Shop Curtain Rods & Decorative Curtain Rods - jcpenney",
                    "domain": "jcpenney.com",
                    "id": "341710690447547116",
                    "image": "https://s-media-cache-ak0.pinimg.com/736x/77/05/01/770501f9eef914cd39629df47cc2856c.jpg",
                    "image236": "https://s-media-cache-ak0.pinimg.com/236x/77/05/01/770501f9eef914cd39629df47cc2856c.jpg",
                    "image60": "https://s-media-cache-ak0.pinimg.com/60x60/77/05/01/770501f9eef914cd39629df47cc2856c.jpg",
                    "is_banned": "",
                    "is_repin": "",
                    "likes": "0",
                    "pin_join": "770501f9eef914cd39629df47cc2856c",
                    "pinner": "341710827885173445",
                    "place": "",
                    "price": "0",
                    "price_currency": "USD",
                    "repins": "1",
                    "source": "http://www.jcpenney.com/dotcom/window/hardware-/cat.jump?id=cat100260231&Ns=PLH&pageSize=96",
                    "title": "Future house stuff",
                    "type": "pin",
                    "url": "https://www.pinterest.com/pin/341710690447547116/",
                    "via_pinner": ""
                },
                "_type": "pin"
            },
            {
                "_id": "229754018459942359",
                "_index": "pinterest",
                "_score": 0.50035363,
                "_source": {
                    "board": "229754087179046880",
                    "comment_count": "0",
                    "created": "Tue, 31 Jan 2012 18:59:55 +0000",
                    "description": "Contemporary, elegant, light window treatment",
                    "domain": "flickr.com",
                    "id": "229754018459942359",
                    "image": "https://s-media-cache-ak0.pinimg.com/736x/54/d3/08/54d308a0f31263a61a204f0e89a12e90.jpg",
                    "image236": "https://s-media-cache-ak0.pinimg.com/236x/54/d3/08/54d308a0f31263a61a204f0e89a12e90.jpg",
                    "image60": "https://s-media-cache-ak0.pinimg.com/60x60/54/d3/08/54d308a0f31263a61a204f0e89a12e90.jpg",
                    "is_banned": "",
                    "is_repin": "",
                    "likes": "0",
                    "pin_join": "54d308a0f31263a61a204f0e89a12e90",
                    "pinner": "229754155898505059",
                    "place": "",
                    "price": "0",
                    "price_currency": "USD",
                    "repins": "1",
                    "source": "http://www.flickr.com/photos/45735558@N02/4992133895/",
                    "title": "window",
                    "type": "pin",
                    "url": "https://www.pinterest.com/pin/229754018459942359/",
                    "via_pinner": ""
                },
                "_type": "pin"
            },
            {
                "_id": "377246906258906061",
                "_index": "pinterest",
                "_score": 0.50003135,
                "_source": {
                    "board": "377246974975537248",
                    "comment_count": "0",
                    "created": "Sun, 13 Apr 2014 16:33:20 +0000",
                    "description": "The Source - Altamont and Spy Optic Storefront window Graphics #YYC #TheSource #SPY #Storefront #windowgraphics #graphic #signage",
                    "domain": "ignition1.com",
                    "id": "377246906258906061",
                    "image": "https://s-media-cache-ak0.pinimg.com/736x/15/99/bb/1599bb6e8ce6f3e710486e6c9bbbc274.jpg",
                    "image236": "https://s-media-cache-ak0.pinimg.com/236x/15/99/bb/1599bb6e8ce6f3e710486e6c9bbbc274.jpg",
                    "image60": "https://s-media-cache-ak0.pinimg.com/60x60/15/99/bb/1599bb6e8ce6f3e710486e6c9bbbc274.jpg",
                    "is_banned": "",
                    "is_repin": "",
                    "likes": "0",
                    "pin_join": "",
                    "pinner": "377247043694888615",
                    "place": "",
                    "price": "0",
                    "price_currency": "USD",
                    "repins": "0",
                    "source": "http://www.ignition1.com/#!windows--walls/c9a6",
                    "title": "Ignition | Sport Store Window Graphic",
                    "type": "pin",
                    "url": "https://www.pinterest.com/pin/377246906258906061/",
                    "via_pinner": ""
                },
                "_type": "pin"
            },
            {
                "_id": "188025353165787070",
                "_index": "pinterest",
                "_score": 0.49840996,
                "_source": {
                    "board": "188025421881714837",
                    "comment_count": "0",
                    "created": "Mon, 24 Jun 2013 00:52:50 +0000",
                    "description": "\"bay Window\" Exterior Design Ideas, Pictures, Remodel, and Decor - page 13",
                    "domain": "houzz.com",
                    "id": "188025353165787070",
                    "image": "https://s-media-cache-ak0.pinimg.com/736x/a8/69/f9/a869f976c6c944e168237be5fd1791ac.jpg",
                    "image236": "https://s-media-cache-ak0.pinimg.com/236x/a8/69/f9/a869f976c6c944e168237be5fd1791ac.jpg",
                    "image60": "https://s-media-cache-ak0.pinimg.com/60x60/a8/69/f9/a869f976c6c944e168237be5fd1791ac.jpg",
                    "is_banned": "",
                    "is_repin": "",
                    "likes": "0",
                    "pin_join": "a869f976c6c944e168237be5fd1791ac",
                    "pinner": "188025490601153118",
                    "place": "",
                    "price": "0",
                    "price_currency": "USD",
                    "repins": "6",
                    "source": "http://www.houzz.com/%22bay-window%22-exterior/p/144",
                    "title": "Curb Appeal",
                    "type": "pin",
                    "url": "https://www.pinterest.com/pin/188025353165787070/",
                    "via_pinner": ""
                },
                "_type": "pin"
            },
            {
                "_id": "397020523372415605",
                "_index": "pinterest",
                "_score": 0.4974459,
                "_source": {
                    "board": "397020592089433259",
                    "comment_count": "0",
                    "created": "Wed, 26 Feb 2014 16:41:45 +0000",
                    "description": "Sandy Point area (not so) A-frame home after remodel/addition. The porthole window adds a nice nautical feel to this little beach house.",
                    "domain": "Uploaded by user",
                    "id": "397020523372415605",
                    "image": "https://s-media-cache-ak0.pinimg.com/736x/a3/89/2e/a3892e0782078a58b0aeb111ce61fc4c.jpg",
                    "image236": "https://s-media-cache-ak0.pinimg.com/236x/a3/89/2e/a3892e0782078a58b0aeb111ce61fc4c.jpg",
                    "image60": "https://s-media-cache-ak0.pinimg.com/60x60/a3/89/2e/a3892e0782078a58b0aeb111ce61fc4c.jpg",
                    "is_banned": "",
                    "is_repin": "",
                    "likes": "0",
                    "pin_join": "",
                    "pinner": "397020660808821971",
                    "place": "",
                    "price": "0",
                    "price_currency": "USD",
                    "repins": "1",
                    "source": "None",
                    "title": "Remodels and Additions",
                    "type": "pin",
                    "url": "https://www.pinterest.com/pin/397020523372415605/",
                    "via_pinner": ""
                },
                "_type": "pin"
            },
            {
                "_id": "256705247482730115",
                "_index": "pinterest",
                "_score": 0.49741358,
                "_source": {
                    "board": "256705316199095213",
                    "comment_count": "0",
                    "created": "Thu, 09 May 2013 18:26:02 +0000",
                    "description": "I like the use of the old window ...",
                    "domain": "hayneedle.com",
                    "id": "256705247482730115",
                    "image": "https://s-media-cache-ak0.pinimg.com/736x/e9/2d/a8/e92da8647c4055cba41609bd8f7a0c38.jpg",
                    "image236": "https://s-media-cache-ak0.pinimg.com/236x/e9/2d/a8/e92da8647c4055cba41609bd8f7a0c38.jpg",
                    "image60": "https://s-media-cache-ak0.pinimg.com/60x60/e9/2d/a8/e92da8647c4055cba41609bd8f7a0c38.jpg",
                    "is_banned": "",
                    "is_repin": "",
                    "likes": "1",
                    "pin_join": "e92da8647c4055cba41609bd8f7a0c38",
                    "pinner": "256705384918550805",
                    "place": "",
                    "price": "0",
                    "price_currency": "USD",
                    "repins": "1",
                    "source": "http://www.hayneedle.com/sale/rectanglemetaledgleywindowboxplanter.cfm?styleboardID=16",
                    "title": "Rectangle Metal Edgley Window Box Planter | www",
                    "type": "pin",
                    "url": "https://www.pinterest.com/pin/256705247482730115/",
                    "via_pinner": ""
                },
                "_type": "pin"
            },
            {
                "_id": "310115124310452076",
                "_index": "pinterest",
                "_score": 0.49560001,
                "_source": {
                    "board": "310115193029919795",
                    "comment_count": "0",
                    "created": "Sat, 18 Aug 2012 01:19:37 +0000",
                    "description": "Check out the Large Window Decals I created with Vistaprint! Personalize your own Large Window Decals at http://vistaprint.com/window-decal.aspx?pfid=056.  Get full-color custom business cards, banners, checks, Christmas cards, stationery, address labels\u2026",
                    "domain": "vistaprint.com",
                    "id": "310115124310452076",
                    "image": "https://s-media-cache-ak0.pinimg.com/736x/91/10/7d/91107d26c3177cd5c7b078ff3ec6a51c.jpg",
                    "image236": "https://s-media-cache-ak0.pinimg.com/236x/91/10/7d/91107d26c3177cd5c7b078ff3ec6a51c.jpg",
                    "image60": "https://s-media-cache-ak0.pinimg.com/60x60/91/10/7d/91107d26c3177cd5c7b078ff3ec6a51c.jpg",
                    "is_banned": "",
                    "is_repin": "",
                    "likes": "0",
                    "pin_join": "",
                    "pinner": "310115261749395890",
                    "place": "",
                    "price": "0",
                    "price_currency": "USD",
                    "repins": "0",
                    "source": "http://www.vistaprint.com/vp/gateway.aspx?s=8828395444&preurl=http://www.vistaprint.com/share-design.aspx%3Fdoc_id%3D2339036568%26shopper_id%3DU445Q3EIGKQG0O2ILI7VKNLI363ZRI40%26xnav%3Dsharesource_7%26share_key%3D07bf09bf-a437-4014-83ce-a39aa0e16e8e",
                    "title": "Fun Dog Grooming Images and Articles",
                    "type": "pin",
                    "url": "https://www.pinterest.com/pin/310115124310452076/",
                    "via_pinner": ""
                },
                "_type": "pin"
            },
            {
                "_id": "92675704805341778",
                "_index": "pinterest",
                "_score": 0.48577163,
                "_source": {
                    "board": "92675773521034876",
                    "comment_count": "0",
                    "created": "Mon, 12 Aug 2013 20:26:45 +0000",
                    "description": "Guest Room Window Treatment",
                    "domain": "smithandnoble.com",
                    "id": "92675704805341778",
                    "image": "https://s-media-cache-ak0.pinimg.com/736x/1b/f4/66/1bf4666a24396b5243cf7ab1449b0708.jpg",
                    "image236": "https://s-media-cache-ak0.pinimg.com/236x/1b/f4/66/1bf4666a24396b5243cf7ab1449b0708.jpg",
                    "image60": "https://s-media-cache-ak0.pinimg.com/60x60/1b/f4/66/1bf4666a24396b5243cf7ab1449b0708.jpg",
                    "is_banned": "",
                    "is_repin": "",
                    "likes": "1",
                    "pin_join": "1bf4666a24396b5243cf7ab1449b0708",
                    "pinner": "92675842240415705",
                    "place": "",
                    "price": "0",
                    "price_currency": "USD",
                    "repins": "19",
                    "source": "http://www.smithandnoble.com/photo-gallery",
                    "title": "Window Treatments",
                    "type": "pin",
                    "url": "https://www.pinterest.com/pin/92675704805341778/",
                    "via_pinner": ""
                },
                "_type": "pin"
            },
            {
                "_id": "195977021258191221",
                "_index": "pinterest",
                "_score": 0.48202145,
                "_source": {
                    "board": "195977089973828054",
                    "comment_count": "0",
                    "created": "Wed, 04 Sep 2013 10:59:36 +0000",
                    "description": "Pinterest is a visual discovery tool that you can use to find ideas for all your projects and interests.",
                    "domain": "blog.shadesshuttersblinds.com",
                    "id": "195977021258191221",
                    "image": "https://s-media-cache-ak0.pinimg.com/736x/4c/30/85/4c3085deb8f2cf57d46765707bcec7bc.jpg",
                    "image236": "https://s-media-cache-ak0.pinimg.com/236x/4c/30/85/4c3085deb8f2cf57d46765707bcec7bc.jpg",
                    "image60": "https://s-media-cache-ak0.pinimg.com/60x60/4c/30/85/4c3085deb8f2cf57d46765707bcec7bc.jpg",
                    "is_banned": "",
                    "is_repin": "",
                    "likes": "0",
                    "pin_join": "",
                    "pinner": "195977158693226665",
                    "place": "",
                    "price": "0",
                    "price_currency": "USD",
                    "repins": "0",
                    "source": "http://blog.shadesshuttersblinds.com/at-home/summer-window-box-ideas/",
                    "title": "** The City **",
                    "type": "pin",
                    "url": "https://www.pinterest.com/pin/195977021258191221/",
                    "via_pinner": ""
                },
                "_type": "pin"
            }
        ],
        "max_score": 1.6194504,
        "total": 184410
    },
    "timed_out": false,
    "took": 633
}
